day-1/and3.v
module and_3 (
    input a, b, c,
    output y
);

    assign y = a & b & c;

endmodule

day -1/day1-p/andtb3.v
module and_3_tb;

reg a, b, c;
wire y;

and_3 uut(
    .a(a),
    .b(b),
    .c(c),
    .y(y)
);

initial begin
    $dumpfile("and_3.vcd");
    $dumpvars(0, and_3_tb);

    a=0; b=0; c=0; 
    #10;

    a=0; b=0; c=1;
    #10;


    a=0; b=1; c=0;
    #10;

    a=0; b=1; c=1;
    #10;

    a=1; b=0; c=0;
    #10;

    a=1; b=0; c=1;
    #10;

    a=1; b=1; c=0;
    #10;

    a=1; b=1; c=1;
    #10;

    $finish;


end



endmodule

day -1/day1-p/and_3.vcd
$date
	Fri May 15 22:15:37 2026
$end
$version
	Icarus Verilog
$end
$timescale
	1s
$end
$scope module and_3_tb $end
$var wire 1 ! y $end
$var reg 1 " a $end
$var reg 1 # b $end
$var reg 1 $ c $end
$scope module uut $end
$var wire 1 " a $end
$var wire 1 # b $end
$var wire 1 $ c $end
$var wire 1 ! y $end
$upscope $end
$upscope $end
$enddefinitions $end
$comment Show the parameter values. $end
$dumpall
$end
#0
$dumpvars
0$
0#
0"
0!
$end
#10
1$
#20
0$
1#
#30
1$
#40
0$
0#
1"
#50
1$
#60
0$
1#
#70
1!
1$
