day-15/p_counter.v
module p_counter #(parameter WIDTH = 4)
 (
    input clk, reset,
    output reg [WIDTH-1:0]counter
);
    always @(posedge clk or posedge reset) begin
        if (reset == 0) begin
            counter <= counter + 1;
        end else begin
            counter <= 0;
        end
    end
endmodule

day-15/p_countertb.v
module p_counter_tb ;

reg clk, r;
wire [3:0]counter_4;
wire [7:0]counter_8;
// 4-bit  counter
p_counter #(4) uut1(
    .clk(clk),
    .reset(r),
    .counter(counter_4)
);
// 8-bit counter
p_counter #(8) uut2(
    .clk(clk),
    .reset(r),
    .counter(counter_8)
);

always #5 clk = ~clk;
initial begin
    clk=0;
    r=1;

    #10 r=0;

    #200;
    $finish;
end

initial begin
    $display("PARAMETER_COUNTER");
    $monitor("time=%0t | reset= %b | clk= %b | counter_4= %b | counter_8= %b",$time,r,clk,counter_4,counter_8);
end

initial begin
    $dumpfile("parameter_counter.vcd");
    $dumpvars(0,p_counter_tb);

end

    
endmodule

day-15/parameter_counter.vcd
$date
	Wed Jun 03 08:26:42 2026
$end
$version
	Icarus Verilog
$end
$timescale
	1s
$end
$scope module p_counter_tb $end
$var wire 8 ! counter_8 [7:0] $end
$var wire 4 " counter_4 [3:0] $end
$var reg 1 # clk $end
$var reg 1 $ r $end
$scope module uut1 $end
$var wire 1 # clk $end
$var wire 1 $ reset $end
$var parameter 32 % WIDTH $end
$var reg 4 & counter [3:0] $end
$upscope $end
$scope module uut2 $end
$var wire 1 # clk $end
$var wire 1 $ reset $end
$var parameter 32 ' WIDTH $end
$var reg 8 ( counter [7:0] $end
$upscope $end
$upscope $end
$enddefinitions $end
$comment Show the parameter values. $end
$dumpall
b1000 '
b100 %
$end
#0
$dumpvars
b0 (
b0 &
1$
0#
b0 "
b0 !
$end
#5
1#
#10
0#
0$
#15
b1 "
b1 &
b1 !
b1 (
1#
#20
0#
#25
b10 !
b10 (
b10 "
b10 &
1#
#30
0#
#35
b11 "
b11 &
b11 !
b11 (
1#
#40
0#
#45
b100 !
b100 (
b100 "
b100 &
1#
#50
0#
#55
b101 "
b101 &
b101 !
b101 (
1#
#60
0#
#65
b110 !
b110 (
b110 "
b110 &
1#
#70
0#
#75
b111 "
b111 &
b111 !
b111 (
1#
#80
0#
#85
b1000 !
b1000 (
b1000 "
b1000 &
1#
#90
0#
#95
b1001 "
b1001 &
b1001 !
b1001 (
1#
#100
0#
#105
b1010 !
b1010 (
b1010 "
b1010 &
1#
#110
0#
#115
b1011 "
b1011 &
b1011 !
b1011 (
1#
#120
0#
#125
b1100 !
b1100 (
b1100 "
b1100 &
1#
#130
0#
#135
b1101 "
b1101 &
b1101 !
b1101 (
1#
#140
0#
#145
b1110 !
b1110 (
b1110 "
b1110 &
1#
#150
0#
#155
b1111 "
b1111 &
b1111 !
b1111 (
1#
#160
0#
#165
b10000 !
b10000 (
b0 "
b0 &
1#
#170
0#
#175
b1 "
b1 &
b10001 !
b10001 (
1#
#180
0#
#185
b10010 !
b10010 (
b10 "
b10 &
1#
#190
0#
#195
b11 "
b11 &
b10011 !
b10011 (
1#
#200
0#
#205
b10100 !
b10100 (
b100 "
b100 &
1#
