day-12/sr.v
//Shift Register {series input series output(siso)}
/*
Concept

Suppose input sequence is:

1 → 0 → 1 → 1

After each clock pulse, bits shift like this:

Clock	Q3 Q2 Q1 Q0

1	0001
2	0010
3	0101
4	1011
*/

module sr(
    input reset, clk,ip,
    output reg [3:0]q
);
    always @(posedge clk or posedge reset) begin

        if (reset) begin
            q <= 4'b0000;
        end else begin
            q <= {q[2:0],ip}; // left shift register
           // q <= {ip,q[3:1]}; // right shift register


        end
        
    end
endmodule

day-12/srtb.v
module srtb;

reg ip,clk,r;
wire [3:0]q;

sr uut (

    .ip(ip),
    .clk(clk),
    .reset(r),
    .q(q)
);

always #5 clk = ~clk;
initial begin
    $dumpfile("sr.vcd");
    $dumpvars(0,srtb);
    clk=0;
    r=1;
    #10;
    r=0;
    $display("shift register");
    //lift shift register
    $monitor("time=%0t|reset=%b|clk=%b|ip=%b | q=%b",$time,r,clk,ip,q);
    //right shift register
   // $monitor("time=%0t | clk=%b | q=%b | ip=%b",$time , clk, q , ip);


    ip=1;
    #10;

    ip=0;
    #10;

    ip=1;
    #10;

    ip=1;
    #10;

    $finish;
    
end


    
endmodule

day-12/sr.vcd
$date
	Fri May 29 17:33:43 2026
$end
$version
	Icarus Verilog
$end
$timescale
	1s
$end
$scope module srtb $end
$var wire 4 ! q [3:0] $end
$var reg 1 " clk $end
$var reg 1 # ip $end
$var reg 1 $ r $end
$scope module uut $end
$var wire 1 " clk $end
$var wire 1 # ip $end
$var wire 1 $ reset $end
$var reg 4 % q [3:0] $end
$upscope $end
$upscope $end
$enddefinitions $end
$comment Show the parameter values. $end
$dumpall
$end
#0
$dumpvars
b0 %
1$
x#
0"
b0 !
$end
#5
1"
#10
0"
1#
0$
#15
b1 !
b1 %
1"
#20
0"
0#
#25
b10 !
b10 %
1"
#30
0"
1#
#35
b101 !
b101 %
1"
#40
0"
#45
b1011 !
b1011 %
1"
