day-19/tl.v
module traffic_light (
    input clk, reset,
    output reg RED, 
    output reg YELLOW,
    output reg GREEN
);
    parameter red =2'b00 ;
    parameter green =2'b01 ;
    parameter yellow =2'b10 ;

    reg [1:0] state;
    reg [1:0] next_state;

    //state workflow

    always @(posedge clk or posedge reset) begin
        if (!reset) begin
            state <= next_state;
        end else begin
            state <= red ;
        end
    end

    //next_state work flow

    always @(*) begin
        case (state)
            red : next_state = green;
            green : next_state = yellow;
            yellow : next_state = red;
            default:next_state = red; 
        endcase
        
    end

    always @(*) begin
        RED = 0;
        GREEN = 0;
        YELLOW = 0;
        case (state)
            red : RED = 1;
            green : GREEN = 1;
            yellow : YELLOW = 1;
            
        endcase
        
    end
endmodule

day-19/tl_tb.v
`timescale 1ns/1ps
module traffic_light_tb;
reg clk , reset;
wire r , g , y;

traffic_light uut(
    .clk(clk),
    .reset(reset),
    .RED(r),
    .YELLOW(y),
    .GREEN(g)
);

always #5 clk = ~clk;

initial begin
     clk = 0;
    reset = 1;
    #10;
   
    reset = 0;
    #60;
    $finish;
        
end

initial begin
    $monitor("time =%0t | reset=%b | clk=%b | red=%b | green=%b | yellow=%b",$time,reset,clk,r,g,y);
end

initial begin
    $dumpfile("tl.vcd");
    $dumpvars(0,traffic_light_tb);
end    

endmodule

day-19/tl.vcd
$date
	Fri Jun 05 19:01:18 2026
$end
$version
	Icarus Verilog
$end
$timescale
	1ps
$end
$scope module traffic_light_tb $end
$var wire 1 ! y $end
$var wire 1 " r $end
$var wire 1 # g $end
$var reg 1 $ clk $end
$var reg 1 % reset $end
$scope module uut $end
$var wire 1 $ clk $end
$var wire 1 % reset $end
$var parameter 2 & green $end
$var parameter 2 ' red $end
$var parameter 2 ( yellow $end
$var reg 1 # GREEN $end
$var reg 1 " RED $end
$var reg 1 ! YELLOW $end
$var reg 2 ) next_state [1:0] $end
$var reg 2 * state [1:0] $end
$upscope $end
$upscope $end
$enddefinitions $end
$comment Show the parameter values. $end
$dumpall
b10 (
b0 '
b1 &
$end
#0
$dumpvars
b0 *
b1 )
1%
0$
0#
1"
0!
$end
#5000
1$
#10000
0$
0%
#15000
b10 )
1#
0"
b1 *
1$
#20000
0$
#25000
1!
0#
b0 )
b10 *
1$
#30000
0$
#35000
b1 )
1"
0!
b0 *
1$
#40000
0$
#45000
1#
0"
b10 )
b1 *
1$
#50000
0$
#55000
b0 )
1!
0#
b10 *
1$
#60000
0$
#65000
1"
0!
b1 )
b0 *
1$
