day-22/full_task.v
/*
Challenge 3 — Full Adder Verification Using Task
*/

module full (
    input a , b, c_in,
    output sum , carry
);
    assign {carry,sum} = a + b + c_in ;
endmodule

day-22/full_task_tb.v
module full_task_tb;
reg a, b, c_in;
wire sum , carry;

full uut(
    .a(a),
    .b(b),
    .c_in(c_in),
    .sum(sum),
    .carry(carry)
);


    task full_adder;
    input ta ;
    input tb ;
    input tc ;
    begin
        a = ta;
        b = tb;
        c_in = tc;
        #10;
    end
    
    endtask

initial begin
    $dumpfile("full_adder.vcd");
    $dumpvars(0,full_task_tb);

    $monitor("time=%0t | a = %b | b = %b | c_in = %b | sum = %b | carry = %b |",$time,a,b,c_in,sum,carry);

    full_adder(0,0,0);
    full_adder(0,0,1);
    full_adder(0,1,0);
    full_adder(0,1,1);
    full_adder(1,0,0);
    full_adder(1,0,1);
    full_adder(1,1,0);
    full_adder(1,1,1);
    
end


    
endmodule

day-22/full_adder.vcd
$date
	Sun Jun 07 13:11:40 2026
$end
$version
	Icarus Verilog
$end
$timescale
	1s
$end
$scope module full_task_tb $end
$var wire 1 ! sum $end
$var wire 1 " carry $end
$var reg 1 # a $end
$var reg 1 $ b $end
$var reg 1 % c_in $end
$scope module uut $end
$var wire 1 # a $end
$var wire 1 $ b $end
$var wire 1 % c_in $end
$var wire 1 ! sum $end
$var wire 1 " carry $end
$upscope $end
$scope task full_adder $end
$var reg 1 & ta $end
$var reg 1 ' tb $end
$var reg 1 ( tc $end
$upscope $end
$upscope $end
$enddefinitions $end
$comment Show the parameter values. $end
$dumpall
$end
#0
$dumpvars
0(
0'
0&
0%
0$
0#
0"
0!
$end
#10
1!
1%
1(
#20
0%
1$
0(
1'
#30
0!
1"
1%
1(
#40
0"
1!
0%
0$
1#
0(
0'
1&
#50
0!
1"
1%
1(
#60
0%
1$
0(
1'
#70
1!
1%
1(
