day-24/loop_adder.v
///2-bit Adder

module loop_2bit (
    input [1:0]a,
    input [1:0]b,
    output [2:0]sum
);
    assign sum = a + b ;
endmodule

day-24/loop_adder_tb.v
module loop_2bit_adder ;
reg [1:0]a ;
reg [1:0]b;
wire [2:0]sum;
integer i , j;

loop_2bit uut(
    .a(a),
    .b(b),
    .sum(sum)
);


initial begin
    $dumpfile("loop_adder.vcd");
    $dumpvars(0,loop_2bit_adder);
    $monitor("time=%0t | a=%b | b=%b | sum=%b",$time,a,b,sum);

    for ( i = 0 ; i<4 ; i++ ) begin
        for (j = 0; j<4 ; j++ ) begin
            a = i ;
            b = j ;
            #10;            
        end
    end
    $finish;
end
    
endmodule

day-24/loop_adder.vcd
$date
	Sun Jun 07 20:50:42 2026
$end
$version
	Icarus Verilog
$end
$timescale
	1s
$end
$scope module loop_2bit_adder $end
$var wire 3 ! sum [2:0] $end
$var reg 2 " a [1:0] $end
$var reg 2 # b [1:0] $end
$var integer 32 $ i [31:0] $end
$var integer 32 % j [31:0] $end
$scope module uut $end
$var wire 2 & a [1:0] $end
$var wire 2 ' b [1:0] $end
$var wire 3 ( sum [2:0] $end
$upscope $end
$upscope $end
$enddefinitions $end
$comment Show the parameter values. $end
$dumpall
$end
#0
$dumpvars
b0 (
b0 '
b0 &
b0 %
b0 $
b0 #
b0 "
b0 !
$end
#10
b1 !
b1 (
b1 #
b1 '
b1 %
#20
b10 !
b10 (
b10 #
b10 '
b10 %
#30
b11 !
b11 (
b11 #
b11 '
b11 %
#40
b0 #
b0 '
b1 !
b1 (
b1 "
b1 &
b1 $
b0 %
#50
b10 !
b10 (
b1 #
b1 '
b1 %
#60
b11 !
b11 (
b10 #
b10 '
b10 %
#70
b100 !
b100 (
b11 #
b11 '
b11 %
#80
b0 #
b0 '
b10 !
b10 (
b10 "
b10 &
b10 $
b0 %
#90
b11 !
b11 (
b1 #
b1 '
b1 %
#100
b100 !
b100 (
b10 #
b10 '
b10 %
#110
b101 !
b101 (
b11 #
b11 '
b11 %
#120
b0 #
b0 '
b11 !
b11 (
b11 "
b11 &
b11 $
b0 %
#130
b100 !
b100 (
b1 #
b1 '
b1 %
#140
b101 !
b101 (
b10 #
b10 '
b10 %
#150
b110 !
b110 (
b11 #
b11 '
b11 %
#160
b100 $
b100 %
