day-24/self_check_full_adder.v
module full_adder (
    input [2:0]a,
    input [2:0]b,
    input [2:0]cin,
    output [3:0]sum,
    output [3:0]carry
);

assign {carry ,sum} = a + b + cin ;
    
endmodule

day-24/self_check_full_adder_tb.v
module self_check_full_adder_tb ;

reg [2:0]a;
reg [2:0]b;
reg [2:0]cin;

wire [3:0]sum;
wire [3:0]carry;

integer i , j ,k;

full_adder uut(
    .a(a),
    .b(b),
    .cin(cin),
    .sum(sum),
    .carry(carry)
);

initial begin
    $dumpfile("self_check_full_adder.vcd");
    $dumpvars(0,self_check_full_adder_tb);
    

    for (i = 0; i < 8 ; i++) begin
        for (j = 0; j < 8 ; j++ ) begin
            for (k =0 ; k < 8; k++ ) begin

            a = i;
            b = j;
            cin = k;
            #10;
            if ({carry,sum} == (a + b + cin)) begin
                $display("PASS time=%0t | a=%b | b=%b | c_in=%b | sum=%b |carry=%b |",$time,a,b,cin,sum,carry);
            end else begin
                $display("NO time=%0t | a=%b | b=%b | c_in=%b | sum=%b |carry=%b |",$time,a,b,cin,sum,carry);
            end
                
            end
            
        end
    end
    $finish;
end
    
endmodule

day-24/self_check_full_adder.vcd
$date
	Sun Jun 07 22:38:07 2026
$end
$version
	Icarus Verilog
$end
$timescale
	1s
$end
$scope module self_check_full_adder_tb $end
$var wire 4 ! sum [3:0] $end
$var wire 4 " carry [3:0] $end
$var reg 3 # a [2:0] $end
$var reg 3 $ b [2:0] $end
$var reg 3 % cin [2:0] $end
$var integer 32 & i [31:0] $end
$var integer 32 ' j [31:0] $end
$var integer 32 ( k [31:0] $end
$scope module uut $end
$var wire 3 ) a [2:0] $end
$var wire 3 * b [2:0] $end
$var wire 3 + cin [2:0] $end
$var wire 4 , sum [3:0] $end
$var wire 4 - carry [3:0] $end
$upscope $end
$upscope $end
$enddefinitions $end
$comment Show the parameter values. $end
$dumpall
$end
#0
$dumpvars
b0 -
b0 ,
b0 +
b0 *
b0 )
b0 (
b0 '
b0 &
b0 %
b0 $
b0 #
b0 "
b0 !
$end
#10
b1 !
b1 ,
b1 %
b1 +
b1 (
#20
b10 !
b10 ,
b10 %
b10 +
b10 (
#30
b11 !
b11 ,
b11 %
b11 +
b11 (
#40
b100 !
b100 ,
b100 %
b100 +
b100 (
#50
b101 !
b101 ,
b101 %
b101 +
b101 (
#60
b110 !
b110 ,
b110 %
b110 +
b110 (
#70
b111 !
b111 ,
b111 %
b111 +
b111 (
#80
b1 !
b1 ,
b0 %
b0 +
b1 $
b1 *
b1 '
b0 (
#90
b10 !
b10 ,
b1 %
b1 +
b1 (
#100
b11 !
b11 ,
b10 %
b10 +
b10 (
#110
b100 !
b100 ,
b11 %
b11 +
b11 (
#120
b101 !
b101 ,
b100 %
b100 +
b100 (
#130
b110 !
b110 ,
b101 %
b101 +
b101 (
#140
b111 !
b111 ,
b110 %
b110 +
b110 (
#150
b1000 !
b1000 ,
b111 %
b111 +
b111 (
#160
b10 !
b10 ,
b0 %
b0 +
b10 $
b10 *
b10 '
b0 (
#170
b11 !
b11 ,
b1 %
b1 +
b1 (
#180
b100 !
b100 ,
b10 %
b10 +
b10 (
#190
b101 !
b101 ,
b11 %
b11 +
b11 (
#200
b110 !
b110 ,
b100 %
b100 +
b100 (
#210
b111 !
b111 ,
b101 %
b101 +
b101 (
#220
b1000 !
b1000 ,
b110 %
b110 +
b110 (
#230
b1001 !
b1001 ,
b111 %
b111 +
b111 (
#240
b11 !
b11 ,
b0 %
b0 +
b11 $
b11 *
b11 '
b0 (
#250
b100 !
b100 ,
b1 %
b1 +
b1 (
#260
b101 !
b101 ,
b10 %
b10 +
b10 (
#270
b110 !
b110 ,
b11 %
b11 +
b11 (
#280
b111 !
b111 ,
b100 %
b100 +
b100 (
#290
b1000 !
b1000 ,
b101 %
b101 +
b101 (
#300
b1001 !
b1001 ,
b110 %
b110 +
b110 (
#310
b1010 !
b1010 ,
b111 %
b111 +
b111 (
#320
b100 !
b100 ,
b0 %
b0 +
b100 $
b100 *
b100 '
b0 (
#330
b101 !
b101 ,
b1 %
b1 +
b1 (
#340
b110 !
b110 ,
b10 %
b10 +
b10 (
#350
b111 !
b111 ,
b11 %
b11 +
b11 (
#360
b1000 !
b1000 ,
b100 %
b100 +
b100 (
#370
b1001 !
b1001 ,
b101 %
b101 +
b101 (
#380
b1010 !
b1010 ,
b110 %
b110 +
b110 (
#390
b1011 !
b1011 ,
b111 %
b111 +
b111 (
#400
b101 !
b101 ,
b0 %
b0 +
b101 $
b101 *
b101 '
b0 (
#410
b110 !
b110 ,
b1 %
b1 +
b1 (
#420
b111 !
b111 ,
b10 %
b10 +
b10 (
#430
b1000 !
b1000 ,
b11 %
b11 +
b11 (
#440
b1001 !
b1001 ,
b100 %
b100 +
b100 (
#450
b1010 !
b1010 ,
b101 %
b101 +
b101 (
#460
b1011 !
b1011 ,
b110 %
b110 +
b110 (
#470
b1100 !
b1100 ,
b111 %
b111 +
b111 (
#480
b110 !
b110 ,
b0 %
b0 +
b110 $
b110 *
b110 '
b0 (
#490
b111 !
b111 ,
b1 %
b1 +
b1 (
#500
b1000 !
b1000 ,
b10 %
b10 +
b10 (
#510
b1001 !
b1001 ,
b11 %
b11 +
b11 (
#520
b1010 !
b1010 ,
b100 %
b100 +
b100 (
#530
b1011 !
b1011 ,
b101 %
b101 +
b101 (
#540
b1100 !
b1100 ,
b110 %
b110 +
b110 (
#550
b1101 !
b1101 ,
b111 %
b111 +
b111 (
#560
b111 !
b111 ,
b0 %
b0 +
b111 $
b111 *
b111 '
b0 (
#570
b1000 !
b1000 ,
b1 %
b1 +
b1 (
#580
b1001 !
b1001 ,
b10 %
b10 +
b10 (
#590
b1010 !
b1010 ,
b11 %
b11 +
b11 (
#600
b1011 !
b1011 ,
b100 %
b100 +
b100 (
#610
b1100 !
b1100 ,
b101 %
b101 +
b101 (
#620
b1101 !
b1101 ,
b110 %
b110 +
b110 (
#630
b1110 !
b1110 ,
b111 %
b111 +
b111 (
#640
b1 !
b1 ,
b0 %
b0 +
b0 $
b0 *
b1 #
b1 )
b1 &
b0 '
b0 (
#650
b10 !
b10 ,
b1 %
b1 +
b1 (
#660
b11 !
b11 ,
b10 %
b10 +
b10 (
#670
b100 !
b100 ,
b11 %
b11 +
b11 (
#680
b101 !
b101 ,
b100 %
b100 +
b100 (
#690
b110 !
b110 ,
b101 %
b101 +
b101 (
#700
b111 !
b111 ,
b110 %
b110 +
b110 (
#710
b1000 !
b1000 ,
b111 %
b111 +
b111 (
#720
b10 !
b10 ,
b0 %
b0 +
b1 $
b1 *
b1 '
b0 (
#730
b11 !
b11 ,
b1 %
b1 +
b1 (
#740
b100 !
b100 ,
b10 %
b10 +
b10 (
#750
b101 !
b101 ,
b11 %
b11 +
b11 (
#760
b110 !
b110 ,
b100 %
b100 +
b100 (
#770
b111 !
b111 ,
b101 %
b101 +
b101 (
#780
b1000 !
b1000 ,
b110 %
b110 +
b110 (
#790
b1001 !
b1001 ,
b111 %
b111 +
b111 (
#800
b11 !
b11 ,
b0 %
b0 +
b10 $
b10 *
b10 '
b0 (
#810
b100 !
b100 ,
b1 %
b1 +
b1 (
#820
b101 !
b101 ,
b10 %
b10 +
b10 (
#830
b110 !
b110 ,
b11 %
b11 +
b11 (
#840
b111 !
b111 ,
b100 %
b100 +
b100 (
#850
b1000 !
b1000 ,
b101 %
b101 +
b101 (
#860
b1001 !
b1001 ,
b110 %
b110 +
b110 (
#870
b1010 !
b1010 ,
b111 %
b111 +
b111 (
#880
b100 !
b100 ,
b0 %
b0 +
b11 $
b11 *
b11 '
b0 (
#890
b101 !
b101 ,
b1 %
b1 +
b1 (
#900
b110 !
b110 ,
b10 %
b10 +
b10 (
#910
b111 !
b111 ,
b11 %
b11 +
b11 (
#920
b1000 !
b1000 ,
b100 %
b100 +
b100 (
#930
b1001 !
b1001 ,
b101 %
b101 +
b101 (
#940
b1010 !
b1010 ,
b110 %
b110 +
b110 (
#950
b1011 !
b1011 ,
b111 %
b111 +
b111 (
#960
b101 !
b101 ,
b0 %
b0 +
b100 $
b100 *
b100 '
b0 (
#970
b110 !
b110 ,
b1 %
b1 +
b1 (
#980
b111 !
b111 ,
b10 %
b10 +
b10 (
#990
b1000 !
b1000 ,
b11 %
b11 +
b11 (
#1000
b1001 !
b1001 ,
b100 %
b100 +
b100 (
#1010
b1010 !
b1010 ,
b101 %
b101 +
b101 (
#1020
b1011 !
b1011 ,
b110 %
b110 +
b110 (
#1030
b1100 !
b1100 ,
b111 %
b111 +
b111 (
#1040
b110 !
b110 ,
b0 %
b0 +
b101 $
b101 *
b101 '
b0 (
#1050
b111 !
b111 ,
b1 %
b1 +
b1 (
#1060
b1000 !
b1000 ,
b10 %
b10 +
b10 (
#1070
b1001 !
b1001 ,
b11 %
b11 +
b11 (
#1080
b1010 !
b1010 ,
b100 %
b100 +
b100 (
#1090
b1011 !
b1011 ,
b101 %
b101 +
b101 (
#1100
b1100 !
b1100 ,
b110 %
b110 +
b110 (
#1110
b1101 !
b1101 ,
b111 %
b111 +
b111 (
#1120
b111 !
b111 ,
b0 %
b0 +
b110 $
b110 *
b110 '
b0 (
#1130
b1000 !
b1000 ,
b1 %
b1 +
b1 (
#1140
b1001 !
b1001 ,
b10 %
b10 +
b10 (
#1150
b1010 !
b1010 ,
b11 %
b11 +
b11 (
#1160
b1011 !
b1011 ,
b100 %
b100 +
b100 (
#1170
b1100 !
b1100 ,
b101 %
b101 +
b101 (
#1180
b1101 !
b1101 ,
b110 %
b110 +
b110 (
#1190
b1110 !
b1110 ,
b111 %
b111 +
b111 (
#1200
b1000 !
b1000 ,
b0 %
b0 +
b111 $
b111 *
b111 '
b0 (
#1210
b1001 !
b1001 ,
b1 %
b1 +
b1 (
#1220
b1010 !
b1010 ,
b10 %
b10 +
b10 (
#1230
b1011 !
b1011 ,
b11 %
b11 +
b11 (
#1240
b1100 !
b1100 ,
b100 %
b100 +
b100 (
#1250
b1101 !
b1101 ,
b101 %
b101 +
b101 (
#1260
b1110 !
b1110 ,
b110 %
b110 +
b110 (
#1270
b1111 !
b1111 ,
b111 %
b111 +
b111 (
#1280
b10 !
b10 ,
b0 %
b0 +
b0 $
b0 *
b10 #
b10 )
b10 &
b0 '
b0 (
#1290
b11 !
b11 ,
b1 %
b1 +
b1 (
#1300
b100 !
b100 ,
b10 %
b10 +
b10 (
#1310
b101 !
b101 ,
b11 %
b11 +
b11 (
#1320
b110 !
b110 ,
b100 %
b100 +
b100 (
#1330
b111 !
b111 ,
b101 %
b101 +
b101 (
#1340
b1000 !
b1000 ,
b110 %
b110 +
b110 (
#1350
b1001 !
b1001 ,
b111 %
b111 +
b111 (
#1360
b11 !
b11 ,
b0 %
b0 +
b1 $
b1 *
b1 '
b0 (
#1370
b100 !
b100 ,
b1 %
b1 +
b1 (
#1380
b101 !
b101 ,
b10 %
b10 +
b10 (
#1390
b110 !
b110 ,
b11 %
b11 +
b11 (
#1400
b111 !
b111 ,
b100 %
b100 +
b100 (
#1410
b1000 !
b1000 ,
b101 %
b101 +
b101 (
#1420
b1001 !
b1001 ,
b110 %
b110 +
b110 (
#1430
b1010 !
b1010 ,
b111 %
b111 +
b111 (
#1440
b100 !
b100 ,
b0 %
b0 +
b10 $
b10 *
b10 '
b0 (
#1450
b101 !
b101 ,
b1 %
b1 +
b1 (
#1460
b110 !
b110 ,
b10 %
b10 +
b10 (
#1470
b111 !
b111 ,
b11 %
b11 +
b11 (
#1480
b1000 !
b1000 ,
b100 %
b100 +
b100 (
#1490
b1001 !
b1001 ,
b101 %
b101 +
b101 (
#1500
b1010 !
b1010 ,
b110 %
b110 +
b110 (
#1510
b1011 !
b1011 ,
b111 %
b111 +
b111 (
#1520
b101 !
b101 ,
b0 %
b0 +
b11 $
b11 *
b11 '
b0 (
#1530
b110 !
b110 ,
b1 %
b1 +
b1 (
#1540
b111 !
b111 ,
b10 %
b10 +
b10 (
#1550
b1000 !
b1000 ,
b11 %
b11 +
b11 (
#1560
b1001 !
b1001 ,
b100 %
b100 +
b100 (
#1570
b1010 !
b1010 ,
b101 %
b101 +
b101 (
#1580
b1011 !
b1011 ,
b110 %
b110 +
b110 (
#1590
b1100 !
b1100 ,
b111 %
b111 +
b111 (
#1600
b110 !
b110 ,
b0 %
b0 +
b100 $
b100 *
b100 '
b0 (
#1610
b111 !
b111 ,
b1 %
b1 +
b1 (
#1620
b1000 !
b1000 ,
b10 %
b10 +
b10 (
#1630
b1001 !
b1001 ,
b11 %
b11 +
b11 (
#1640
b1010 !
b1010 ,
b100 %
b100 +
b100 (
#1650
b1011 !
b1011 ,
b101 %
b101 +
b101 (
#1660
b1100 !
b1100 ,
b110 %
b110 +
b110 (
#1670
b1101 !
b1101 ,
b111 %
b111 +
b111 (
#1680
b111 !
b111 ,
b0 %
b0 +
b101 $
b101 *
b101 '
b0 (
#1690
b1000 !
b1000 ,
b1 %
b1 +
b1 (
#1700
b1001 !
b1001 ,
b10 %
b10 +
b10 (
#1710
b1010 !
b1010 ,
b11 %
b11 +
b11 (
#1720
b1011 !
b1011 ,
b100 %
b100 +
b100 (
#1730
b1100 !
b1100 ,
b101 %
b101 +
b101 (
#1740
b1101 !
b1101 ,
b110 %
b110 +
b110 (
#1750
b1110 !
b1110 ,
b111 %
b111 +
b111 (
#1760
b1000 !
b1000 ,
b0 %
b0 +
b110 $
b110 *
b110 '
b0 (
#1770
b1001 !
b1001 ,
b1 %
b1 +
b1 (
#1780
b1010 !
b1010 ,
b10 %
b10 +
b10 (
#1790
b1011 !
b1011 ,
b11 %
b11 +
b11 (
#1800
b1100 !
b1100 ,
b100 %
b100 +
b100 (
#1810
b1101 !
b1101 ,
b101 %
b101 +
b101 (
#1820
b1110 !
b1110 ,
b110 %
b110 +
b110 (
#1830
b1111 !
b1111 ,
b111 %
b111 +
b111 (
#1840
b1001 !
b1001 ,
b0 %
b0 +
b111 $
b111 *
b111 '
b0 (
#1850
b1010 !
b1010 ,
b1 %
b1 +
b1 (
#1860
b1011 !
b1011 ,
b10 %
b10 +
b10 (
#1870
b1100 !
b1100 ,
b11 %
b11 +
b11 (
#1880
b1101 !
b1101 ,
b100 %
b100 +
b100 (
#1890
b1110 !
b1110 ,
b101 %
b101 +
b101 (
#1900
b1111 !
b1111 ,
b110 %
b110 +
b110 (
#1910
b0 !
b0 ,
b1 "
b1 -
b111 %
b111 +
b111 (
#1920
b0 "
b0 -
b11 !
b11 ,
b0 %
b0 +
b0 $
b0 *
b11 #
b11 )
b11 &
b0 '
b0 (
#1930
b100 !
b100 ,
b1 %
b1 +
b1 (
#1940
b101 !
b101 ,
b10 %
b10 +
b10 (
#1950
b110 !
b110 ,
b11 %
b11 +
b11 (
#1960
b111 !
b111 ,
b100 %
b100 +
b100 (
#1970
b1000 !
b1000 ,
b101 %
b101 +
b101 (
#1980
b1001 !
b1001 ,
b110 %
b110 +
b110 (
#1990
b1010 !
b1010 ,
b111 %
b111 +
b111 (
#2000
b100 !
b100 ,
b0 %
b0 +
b1 $
b1 *
b1 '
b0 (
#2010
b101 !
b101 ,
b1 %
b1 +
b1 (
#2020
b110 !
b110 ,
b10 %
b10 +
b10 (
#2030
b111 !
b111 ,
b11 %
b11 +
b11 (
#2040
b1000 !
b1000 ,
b100 %
b100 +
b100 (
#2050
b1001 !
b1001 ,
b101 %
b101 +
b101 (
#2060
b1010 !
b1010 ,
b110 %
b110 +
b110 (
#2070
b1011 !
b1011 ,
b111 %
b111 +
b111 (
#2080
b101 !
b101 ,
b0 %
b0 +
b10 $
b10 *
b10 '
b0 (
#2090
b110 !
b110 ,
b1 %
b1 +
b1 (
#2100
b111 !
b111 ,
b10 %
b10 +
b10 (
#2110
b1000 !
b1000 ,
b11 %
b11 +
b11 (
#2120
b1001 !
b1001 ,
b100 %
b100 +
b100 (
#2130
b1010 !
b1010 ,
b101 %
b101 +
b101 (
#2140
b1011 !
b1011 ,
b110 %
b110 +
b110 (
#2150
b1100 !
b1100 ,
b111 %
b111 +
b111 (
#2160
b110 !
b110 ,
b0 %
b0 +
b11 $
b11 *
b11 '
b0 (
#2170
b111 !
b111 ,
b1 %
b1 +
b1 (
#2180
b1000 !
b1000 ,
b10 %
b10 +
b10 (
#2190
b1001 !
b1001 ,
b11 %
b11 +
b11 (
#2200
b1010 !
b1010 ,
b100 %
b100 +
b100 (
#2210
b1011 !
b1011 ,
b101 %
b101 +
b101 (
#2220
b1100 !
b1100 ,
b110 %
b110 +
b110 (
#2230
b1101 !
b1101 ,
b111 %
b111 +
b111 (
#2240
b111 !
b111 ,
b0 %
b0 +
b100 $
b100 *
b100 '
b0 (
#2250
b1000 !
b1000 ,
b1 %
b1 +
b1 (
#2260
b1001 !
b1001 ,
b10 %
b10 +
b10 (
#2270
b1010 !
b1010 ,
b11 %
b11 +
b11 (
#2280
b1011 !
b1011 ,
b100 %
b100 +
b100 (
#2290
b1100 !
b1100 ,
b101 %
b101 +
b101 (
#2300
b1101 !
b1101 ,
b110 %
b110 +
b110 (
#2310
b1110 !
b1110 ,
b111 %
b111 +
b111 (
#2320
b1000 !
b1000 ,
b0 %
b0 +
b101 $
b101 *
b101 '
b0 (
#2330
b1001 !
b1001 ,
b1 %
b1 +
b1 (
#2340
b1010 !
b1010 ,
b10 %
b10 +
b10 (
#2350
b1011 !
b1011 ,
b11 %
b11 +
b11 (
#2360
b1100 !
b1100 ,
b100 %
b100 +
b100 (
#2370
b1101 !
b1101 ,
b101 %
b101 +
b101 (
#2380
b1110 !
b1110 ,
b110 %
b110 +
b110 (
#2390
b1111 !
b1111 ,
b111 %
b111 +
b111 (
#2400
b1001 !
b1001 ,
b0 %
b0 +
b110 $
b110 *
b110 '
b0 (
#2410
b1010 !
b1010 ,
b1 %
b1 +
b1 (
#2420
b1011 !
b1011 ,
b10 %
b10 +
b10 (
#2430
b1100 !
b1100 ,
b11 %
b11 +
b11 (
#2440
b1101 !
b1101 ,
b100 %
b100 +
b100 (
#2450
b1110 !
b1110 ,
b101 %
b101 +
b101 (
#2460
b1111 !
b1111 ,
b110 %
b110 +
b110 (
#2470
b0 !
b0 ,
b1 "
b1 -
b111 %
b111 +
b111 (
#2480
b0 "
b0 -
b1010 !
b1010 ,
b0 %
b0 +
b111 $
b111 *
b111 '
b0 (
#2490
b1011 !
b1011 ,
b1 %
b1 +
b1 (
#2500
b1100 !
b1100 ,
b10 %
b10 +
b10 (
#2510
b1101 !
b1101 ,
b11 %
b11 +
b11 (
#2520
b1110 !
b1110 ,
b100 %
b100 +
b100 (
#2530
b1111 !
b1111 ,
b101 %
b101 +
b101 (
#2540
b0 !
b0 ,
b1 "
b1 -
b110 %
b110 +
b110 (
#2550
b1 !
b1 ,
b111 %
b111 +
b111 (
#2560
b0 "
b0 -
b100 !
b100 ,
b0 %
b0 +
b0 $
b0 *
b100 #
b100 )
b100 &
b0 '
b0 (
#2570
b101 !
b101 ,
b1 %
b1 +
b1 (
#2580
b110 !
b110 ,
b10 %
b10 +
b10 (
#2590
b111 !
b111 ,
b11 %
b11 +
b11 (
#2600
b1000 !
b1000 ,
b100 %
b100 +
b100 (
#2610
b1001 !
b1001 ,
b101 %
b101 +
b101 (
#2620
b1010 !
b1010 ,
b110 %
b110 +
b110 (
#2630
b1011 !
b1011 ,
b111 %
b111 +
b111 (
#2640
b101 !
b101 ,
b0 %
b0 +
b1 $
b1 *
b1 '
b0 (
#2650
b110 !
b110 ,
b1 %
b1 +
b1 (
#2660
b111 !
b111 ,
b10 %
b10 +
b10 (
#2670
b1000 !
b1000 ,
b11 %
b11 +
b11 (
#2680
b1001 !
b1001 ,
b100 %
b100 +
b100 (
#2690
b1010 !
b1010 ,
b101 %
b101 +
b101 (
#2700
b1011 !
b1011 ,
b110 %
b110 +
b110 (
#2710
b1100 !
b1100 ,
b111 %
b111 +
b111 (
#2720
b110 !
b110 ,
b0 %
b0 +
b10 $
b10 *
b10 '
b0 (
#2730
b111 !
b111 ,
b1 %
b1 +
b1 (
#2740
b1000 !
b1000 ,
b10 %
b10 +
b10 (
#2750
b1001 !
b1001 ,
b11 %
b11 +
b11 (
#2760
b1010 !
b1010 ,
b100 %
b100 +
b100 (
#2770
b1011 !
b1011 ,
b101 %
b101 +
b101 (
#2780
b1100 !
b1100 ,
b110 %
b110 +
b110 (
#2790
b1101 !
b1101 ,
b111 %
b111 +
b111 (
#2800
b111 !
b111 ,
b0 %
b0 +
b11 $
b11 *
b11 '
b0 (
#2810
b1000 !
b1000 ,
b1 %
b1 +
b1 (
#2820
b1001 !
b1001 ,
b10 %
b10 +
b10 (
#2830
b1010 !
b1010 ,
b11 %
b11 +
b11 (
#2840
b1011 !
b1011 ,
b100 %
b100 +
b100 (
#2850
b1100 !
b1100 ,
b101 %
b101 +
b101 (
#2860
b1101 !
b1101 ,
b110 %
b110 +
b110 (
#2870
b1110 !
b1110 ,
b111 %
b111 +
b111 (
#2880
b1000 !
b1000 ,
b0 %
b0 +
b100 $
b100 *
b100 '
b0 (
#2890
b1001 !
b1001 ,
b1 %
b1 +
b1 (
#2900
b1010 !
b1010 ,
b10 %
b10 +
b10 (
#2910
b1011 !
b1011 ,
b11 %
b11 +
b11 (
#2920
b1100 !
b1100 ,
b100 %
b100 +
b100 (
#2930
b1101 !
b1101 ,
b101 %
b101 +
b101 (
#2940
b1110 !
b1110 ,
b110 %
b110 +
b110 (
#2950
b1111 !
b1111 ,
b111 %
b111 +
b111 (
#2960
b1001 !
b1001 ,
b0 %
b0 +
b101 $
b101 *
b101 '
b0 (
#2970
b1010 !
b1010 ,
b1 %
b1 +
b1 (
#2980
b1011 !
b1011 ,
b10 %
b10 +
b10 (
#2990
b1100 !
b1100 ,
b11 %
b11 +
b11 (
#3000
b1101 !
b1101 ,
b100 %
b100 +
b100 (
#3010
b1110 !
b1110 ,
b101 %
b101 +
b101 (
#3020
b1111 !
b1111 ,
b110 %
b110 +
b110 (
#3030
b0 !
b0 ,
b1 "
b1 -
b111 %
b111 +
b111 (
#3040
b0 "
b0 -
b1010 !
b1010 ,
b0 %
b0 +
b110 $
b110 *
b110 '
b0 (
#3050
b1011 !
b1011 ,
b1 %
b1 +
b1 (
#3060
b1100 !
b1100 ,
b10 %
b10 +
b10 (
#3070
b1101 !
b1101 ,
b11 %
b11 +
b11 (
#3080
b1110 !
b1110 ,
b100 %
b100 +
b100 (
#3090
b1111 !
b1111 ,
b101 %
b101 +
b101 (
#3100
b0 !
b0 ,
b1 "
b1 -
b110 %
b110 +
b110 (
#3110
b1 !
b1 ,
b111 %
b111 +
b111 (
#3120
b0 "
b0 -
b1011 !
b1011 ,
b0 %
b0 +
b111 $
b111 *
b111 '
b0 (
#3130
b1100 !
b1100 ,
b1 %
b1 +
b1 (
#3140
b1101 !
b1101 ,
b10 %
b10 +
b10 (
#3150
b1110 !
b1110 ,
b11 %
b11 +
b11 (
#3160
b1111 !
b1111 ,
b100 %
b100 +
b100 (
#3170
b0 !
b0 ,
b1 "
b1 -
b101 %
b101 +
b101 (
#3180
b1 !
b1 ,
b110 %
b110 +
b110 (
#3190
b10 !
b10 ,
b111 %
b111 +
b111 (
#3200
b0 "
b0 -
b101 !
b101 ,
b0 %
b0 +
b0 $
b0 *
b101 #
b101 )
b101 &
b0 '
b0 (
#3210
b110 !
b110 ,
b1 %
b1 +
b1 (
#3220
b111 !
b111 ,
b10 %
b10 +
b10 (
#3230
b1000 !
b1000 ,
b11 %
b11 +
b11 (
#3240
b1001 !
b1001 ,
b100 %
b100 +
b100 (
#3250
b1010 !
b1010 ,
b101 %
b101 +
b101 (
#3260
b1011 !
b1011 ,
b110 %
b110 +
b110 (
#3270
b1100 !
b1100 ,
b111 %
b111 +
b111 (
#3280
b110 !
b110 ,
b0 %
b0 +
b1 $
b1 *
b1 '
b0 (
#3290
b111 !
b111 ,
b1 %
b1 +
b1 (
#3300
b1000 !
b1000 ,
b10 %
b10 +
b10 (
#3310
b1001 !
b1001 ,
b11 %
b11 +
b11 (
#3320
b1010 !
b1010 ,
b100 %
b100 +
b100 (
#3330
b1011 !
b1011 ,
b101 %
b101 +
b101 (
#3340
b1100 !
b1100 ,
b110 %
b110 +
b110 (
#3350
b1101 !
b1101 ,
b111 %
b111 +
b111 (
#3360
b111 !
b111 ,
b0 %
b0 +
b10 $
b10 *
b10 '
b0 (
#3370
b1000 !
b1000 ,
b1 %
b1 +
b1 (
#3380
b1001 !
b1001 ,
b10 %
b10 +
b10 (
#3390
b1010 !
b1010 ,
b11 %
b11 +
b11 (
#3400
b1011 !
b1011 ,
b100 %
b100 +
b100 (
#3410
b1100 !
b1100 ,
b101 %
b101 +
b101 (
#3420
b1101 !
b1101 ,
b110 %
b110 +
b110 (
#3430
b1110 !
b1110 ,
b111 %
b111 +
b111 (
#3440
b1000 !
b1000 ,
b0 %
b0 +
b11 $
b11 *
b11 '
b0 (
#3450
b1001 !
b1001 ,
b1 %
b1 +
b1 (
#3460
b1010 !
b1010 ,
b10 %
b10 +
b10 (
#3470
b1011 !
b1011 ,
b11 %
b11 +
b11 (
#3480
b1100 !
b1100 ,
b100 %
b100 +
b100 (
#3490
b1101 !
b1101 ,
b101 %
b101 +
b101 (
#3500
b1110 !
b1110 ,
b110 %
b110 +
b110 (
#3510
b1111 !
b1111 ,
b111 %
b111 +
b111 (
#3520
b1001 !
b1001 ,
b0 %
b0 +
b100 $
b100 *
b100 '
b0 (
#3530
b1010 !
b1010 ,
b1 %
b1 +
b1 (
#3540
b1011 !
b1011 ,
b10 %
b10 +
b10 (
#3550
b1100 !
b1100 ,
b11 %
b11 +
b11 (
#3560
b1101 !
b1101 ,
b100 %
b100 +
b100 (
#3570
b1110 !
b1110 ,
b101 %
b101 +
b101 (
#3580
b1111 !
b1111 ,
b110 %
b110 +
b110 (
#3590
b0 !
b0 ,
b1 "
b1 -
b111 %
b111 +
b111 (
#3600
b0 "
b0 -
b1010 !
b1010 ,
b0 %
b0 +
b101 $
b101 *
b101 '
b0 (
#3610
b1011 !
b1011 ,
b1 %
b1 +
b1 (
#3620
b1100 !
b1100 ,
b10 %
b10 +
b10 (
#3630
b1101 !
b1101 ,
b11 %
b11 +
b11 (
#3640
b1110 !
b1110 ,
b100 %
b100 +
b100 (
#3650
b1111 !
b1111 ,
b101 %
b101 +
b101 (
#3660
b0 !
b0 ,
b1 "
b1 -
b110 %
b110 +
b110 (
#3670
b1 !
b1 ,
b111 %
b111 +
b111 (
#3680
b0 "
b0 -
b1011 !
b1011 ,
b0 %
b0 +
b110 $
b110 *
b110 '
b0 (
#3690
b1100 !
b1100 ,
b1 %
b1 +
b1 (
#3700
b1101 !
b1101 ,
b10 %
b10 +
b10 (
#3710
b1110 !
b1110 ,
b11 %
b11 +
b11 (
#3720
b1111 !
b1111 ,
b100 %
b100 +
b100 (
#3730
b0 !
b0 ,
b1 "
b1 -
b101 %
b101 +
b101 (
#3740
b1 !
b1 ,
b110 %
b110 +
b110 (
#3750
b10 !
b10 ,
b111 %
b111 +
b111 (
#3760
b0 "
b0 -
b1100 !
b1100 ,
b0 %
b0 +
b111 $
b111 *
b111 '
b0 (
#3770
b1101 !
b1101 ,
b1 %
b1 +
b1 (
#3780
b1110 !
b1110 ,
b10 %
b10 +
b10 (
#3790
b1111 !
b1111 ,
b11 %
b11 +
b11 (
#3800
b0 !
b0 ,
b1 "
b1 -
b100 %
b100 +
b100 (
#3810
b1 !
b1 ,
b101 %
b101 +
b101 (
#3820
b10 !
b10 ,
b110 %
b110 +
b110 (
#3830
b11 !
b11 ,
b111 %
b111 +
b111 (
#3840
b0 "
b0 -
b110 !
b110 ,
b0 %
b0 +
b0 $
b0 *
b110 #
b110 )
b110 &
b0 '
b0 (
#3850
b111 !
b111 ,
b1 %
b1 +
b1 (
#3860
b1000 !
b1000 ,
b10 %
b10 +
b10 (
#3870
b1001 !
b1001 ,
b11 %
b11 +
b11 (
#3880
b1010 !
b1010 ,
b100 %
b100 +
b100 (
#3890
b1011 !
b1011 ,
b101 %
b101 +
b101 (
#3900
b1100 !
b1100 ,
b110 %
b110 +
b110 (
#3910
b1101 !
b1101 ,
b111 %
b111 +
b111 (
#3920
b111 !
b111 ,
b0 %
b0 +
b1 $
b1 *
b1 '
b0 (
#3930
b1000 !
b1000 ,
b1 %
b1 +
b1 (
#3940
b1001 !
b1001 ,
b10 %
b10 +
b10 (
#3950
b1010 !
b1010 ,
b11 %
b11 +
b11 (
#3960
b1011 !
b1011 ,
b100 %
b100 +
b100 (
#3970
b1100 !
b1100 ,
b101 %
b101 +
b101 (
#3980
b1101 !
b1101 ,
b110 %
b110 +
b110 (
#3990
b1110 !
b1110 ,
b111 %
b111 +
b111 (
#4000
b1000 !
b1000 ,
b0 %
b0 +
b10 $
b10 *
b10 '
b0 (
#4010
b1001 !
b1001 ,
b1 %
b1 +
b1 (
#4020
b1010 !
b1010 ,
b10 %
b10 +
b10 (
#4030
b1011 !
b1011 ,
b11 %
b11 +
b11 (
#4040
b1100 !
b1100 ,
b100 %
b100 +
b100 (
#4050
b1101 !
b1101 ,
b101 %
b101 +
b101 (
#4060
b1110 !
b1110 ,
b110 %
b110 +
b110 (
#4070
b1111 !
b1111 ,
b111 %
b111 +
b111 (
#4080
b1001 !
b1001 ,
b0 %
b0 +
b11 $
b11 *
b11 '
b0 (
#4090
b1010 !
b1010 ,
b1 %
b1 +
b1 (
#4100
b1011 !
b1011 ,
b10 %
b10 +
b10 (
#4110
b1100 !
b1100 ,
b11 %
b11 +
b11 (
#4120
b1101 !
b1101 ,
b100 %
b100 +
b100 (
#4130
b1110 !
b1110 ,
b101 %
b101 +
b101 (
#4140
b1111 !
b1111 ,
b110 %
b110 +
b110 (
#4150
b0 !
b0 ,
b1 "
b1 -
b111 %
b111 +
b111 (
