day-28_project/uart_2.v
/*
Challenge 1 — Transmit Another Byte

Change:

Data_in = 8’b11001100;

Expected UART Sequence

Start

0
0
1
1
0
0
1
1

Stop

GTKWave Signals

Tx
Bit_count

*/

module uart (
    input clk , reset ,start,
    input [7:0]data_in,
    output reg busy,
    output reg tx 

);
reg [3:0]bit_counter;
reg [7:0]data_reg;
always @(posedge clk or posedge reset) begin
    if (reset) begin
        tx <= 1;
        busy <= 0;
        bit_counter <= 0;
    end else begin
        if (start && !busy) begin
            tx <= 0;
            busy <= 1;
            data_reg <= data_in;
            bit_counter <= 0;
            
        end 
        else if(busy) begin
            bit_counter <= bit_counter+1;
            case (bit_counter)
                0:tx <= data_reg[0];
                1:tx <= data_reg[1];
                2:tx <= data_reg[2];
                3:tx <= data_reg[3];
                4:tx <= data_reg[4];
                5:tx <= data_reg[5];
                6:tx <= data_reg[6];
                7:tx <= data_reg[7];
                8:
                begin
                    tx <= 1;
                    busy <= 0;
                end
                


                
            endcase

            
        end
        
    end

    
end
    
endmodule

day-28_project/uart_2_tb.v
module uart_tb;
reg clk; 
reg reset; 
reg start;
reg [7:0]data_in ;
wire busy;
wire tx;

uart uut(
    .reset(reset),
    .clk(clk),
    .start(start),
    .data_in(data_in),
    .tx(tx),
    .busy(busy)
);
    always #5 clk = ~clk ;
    initial begin
        $dumpfile("uart.vcd");
        $dumpvars(0,uart_tb);
        $monitor("time=%0t | reset=%b | tx =%b | busy =%b",$time,reset,tx,busy);

///10100101




        clk = 0;
        reset = 1;
        start = 0;
        $display("10100101");
        data_in = 8'b10100101;
        #10 reset=0;
        #10 start = 1;
        #10 start = 0;

        #150 ;

        //11001100
        
        $display(" 11001100");
        clk = 0;
        reset= 1;
        start = 0;
        data_in = 8'b11001100;
        #10 reset=0;
        #10 start = 1;
        #10 start = 0;

        #150 ;

        //11110000
         $display(" 11110000");

        clk = 0;
        reset = 1;
        start = 0;
        data_in = 8'b11110000;
        #10 reset=0;
        #10 start = 1;
        #10 start = 0;

        #150 ;
        $finish;



//11001100

//11110000
    end
endmodule

day-28_project/uart.vcd
$date
	Fri Jun 19 01:45:51 2026
$end
$version
	Icarus Verilog
$end
$timescale
	1s
$end
$scope module uart_tb $end
$var wire 1 ! tx $end
$var wire 1 " busy $end
$var reg 1 # clk $end
$var reg 8 $ data_in [7:0] $end
$var reg 1 % reset $end
$var reg 1 & start $end
$scope module uut $end
$var wire 1 # clk $end
$var wire 8 ' data_in [7:0] $end
$var wire 1 % reset $end
$var wire 1 & start $end
$var reg 4 ( bit_counter [3:0] $end
$var reg 1 " busy $end
$var reg 8 ) data_reg [7:0] $end
$var reg 1 ! tx $end
$upscope $end
$upscope $end
$enddefinitions $end
$comment Show the parameter values. $end
$dumpall
$end
#0
$dumpvars
bx )
b0 (
b10100101 '
0&
1%
b10100101 $
0#
0"
1!
$end
#5
1#
#10
0#
0%
#15
1#
#20
0#
1&
#25
b10100101 )
1"
0!
1#
#30
0#
0&
#35
1!
b1 (
1#
#40
0#
#45
0!
b10 (
1#
#50
0#
#55
1!
b11 (
1#
#60
0#
#65
0!
b100 (
1#
#70
0#
#75
b101 (
1#
#80
0#
#85
1!
b110 (
1#
#90
0#
#95
0!
b111 (
1#
#100
0#
#105
1!
b1000 (
1#
#110
0#
#115
0"
b1001 (
1#
#120
0#
#125
1#
#130
0#
#135
1#
#140
0#
#145
1#
#150
0#
#155
1#
#160
0#
#165
1#
#170
0#
#175
1#
#180
b0 (
b11001100 $
b11001100 '
1%
1#
#185
0#
#190
1#
0%
#195
0#
#200
b11001100 )
1"
0!
1#
1&
#205
0#
#210
b1 (
1#
0&
#215
0#
#220
b10 (
1#
#225
0#
#230
1!
b11 (
1#
#235
0#
#240
b100 (
1#
#245
0#
#250
0!
b101 (
1#
#255
0#
#260
b110 (
1#
#265
0#
#270
1!
b111 (
1#
#275
0#
#280
b1000 (
1#
#285
0#
#290
0"
b1001 (
1#
#295
0#
#300
1#
#305
0#
#310
1#
#315
0#
#320
1#
#325
0#
#330
1#
#335
0#
#340
1#
#345
0#
#350
1#
#355
0#
#360
b0 (
1#
b11110000 $
b11110000 '
1%
#365
0#
#370
1#
0%
#375
0#
#380
b11110000 )
1"
0!
1#
1&
#385
0#
#390
b1 (
1#
0&
#395
0#
#400
b10 (
1#
#405
0#
#410
b11 (
1#
#415
0#
#420
b100 (
1#
#425
0#
#430
1!
b101 (
1#
#435
0#
#440
b110 (
1#
#445
0#
#450
b111 (
1#
#455
0#
#460
b1000 (
1#
#465
0#
#470
0"
b1001 (
1#
