day-6/mux8x1.v
module mux (

    input a, b, c, d, e, f, g, h, s0, s1, s2,
    output y
);
    assign y = s2 ? (s1 ? (s0 ? h : g ) : (s0 ? f : e) ) : (s1 ?  ( s0 ? d : c) : (s0 ? b : a ) );

endmodule

day-6/mux8x1tb.v
module muxtb ;
reg a, b, c, d, e, f, g, h, s0=0, s1=0, s2=0 ;
wire y;

mux uut (
    .a(a),
    .b(b),
    .c(c),
    .d(d),
    .e(e),
    .f(f),
    .g(g),
    .h(h),
    .s0(s0),
    .s1(s1),
    .s2(s2),
    .y(y)
);

initial begin
    $dumpfile("mux8x1.vcd");
    $dumpvars(0, muxtb);
    

    a=0; b=1; c=0; d=1; e=0; f=1; g=0; h=1;
    #10;

    s2=0; s1=0; s0=0;
    #10;

    s2=0; s1=0; s0=1;
    #10;

    s2=0; s1=1; s0=0;
    #10;

    s2=0; s1=1; s0=1;
    #10;

    s2=1; s1=0; s0=0;
    #10;

    s2=1; s1=0; s0=1;
    #10;

    s2=1; s1=1; s0=0;
    #10;

    s2=1; s1=1; s0=1;
    #10;

    $finish;

    

end
    always @(s2 or s1 or s0) begin
       $display("%b %b %b %b %b %b %b %b | %b %b %b | %b ",a,b,c,d,e,f,g,h,s0,s1,s2,y);
    
    end

endmodule

day-6/mux8x1.vcd
$date
	Wed Jun 03 23:03:45 2026
$end
$version
	Icarus Verilog
$end
$timescale
	1s
$end
$scope module muxtb $end
$var wire 1 ! y $end
$var reg 1 " a $end
$var reg 1 # b $end
$var reg 1 $ c $end
$var reg 1 % d $end
$var reg 1 & e $end
$var reg 1 ' f $end
$var reg 1 ( g $end
$var reg 1 ) h $end
$var reg 1 * s0 $end
$var reg 1 + s1 $end
$var reg 1 , s2 $end
$scope module uut $end
$var wire 1 " a $end
$var wire 1 # b $end
$var wire 1 $ c $end
$var wire 1 % d $end
$var wire 1 & e $end
$var wire 1 ' f $end
$var wire 1 ( g $end
$var wire 1 ) h $end
$var wire 1 * s0 $end
$var wire 1 + s1 $end
$var wire 1 , s2 $end
$var wire 1 ! y $end
$upscope $end
$upscope $end
$enddefinitions $end
$comment Show the parameter values. $end
$dumpall
$end
#0
$dumpvars
0,
0+
0*
1)
0(
1'
0&
1%
0$
1#
0"
0!
$end
#20
1!
1*
#30
0!
0*
1+
#40
1!
1*
#50
0!
0*
0+
1,
#60
1!
1*
#70
0!
0*
1+
#80
1!
1*
