day-19/e_tl.v
module e_tl (
    input clk , enable,reset,
    output reg RED,
    output reg YELLOW ,
    output reg GREEN,
    output reg WALK
);

parameter red = 2'b00 ;
parameter yellow = 2'b01 ;
parameter green = 2'b10 ;
parameter walk = 2'b11 ;
reg [1:0]state;
reg [1:0]next_state;

always @(posedge clk or posedge reset) begin

    if (reset) begin
        state <= red;
    end else begin
         if (enable) begin
               state <= next_state ;

    end else begin

        state <= state;       
    end
        
    end
   
    
end

always @(*) begin
    case (state)
         red : next_state = green;
         green : next_state = yellow;
         yellow : next_state = walk;
         walk : next_state = red ; 
        default: next_state = red ; 
    endcase
    
end

always @(*) begin
    RED = 0;
    GREEN = 0;
    YELLOW = 0;
    WALK = 0;

    case (state)
        red: RED = 1;
        green: GREEN = 1;
        yellow: YELLOW = 1; 
        walk: WALK = 1;
        
    endcase
end
    
endmodule

day-21_project/traffic_light_tb.v

module traffic_light_tb;
reg clk , enable,reset;
wire r , g , y ,w;

e_tl uut(
    .clk(clk),
    .reset(reset),
    .enable(enable),
    .RED(r),
    .YELLOW(y),
    .GREEN(g),
    .WALK(w)
);

always #5 clk = ~clk;

initial begin
     clk = 0;
     enable = 0;
     reset=1;
     #10;
      $monitor("time =%0t |reset=%b| enable=%b | clk=%b | red=%b | green=%b | yellow=%b | walk=%b",$time,reset,enable,clk,r,g,y,w);
     reset=0;
    enable = 1;
    #30;
   
    enable = 0;
    #10;

    enable = 1;
    #30;
    $finish;
        
end



initial begin
    $dumpfile("e_tl.vcd");
    $dumpvars(0,traffic_light_tb);
end    

endmodule

day-21_project/traffic_light.vcd
$date
	Sat Jun 06 22:28:17 2026
$end
$version
	Icarus Verilog
$end
$timescale
	1s
$end
$scope module traffic_light_tb $end
$var wire 1 ! y $end
$var wire 1 " w $end
$var wire 1 # r $end
$var wire 1 $ g $end
$var reg 1 % clk $end
$var reg 1 & enable $end
$var reg 1 ' reset $end
$scope module uut $end
$var wire 1 % clk $end
$var wire 1 & enable $end
$var wire 1 ' reset $end
$var parameter 2 ( green $end
$var parameter 2 ) red $end
$var parameter 2 * walk $end
$var parameter 2 + yellow $end
$var reg 1 $ GREEN $end
$var reg 1 # RED $end
$var reg 1 " WALK $end
$var reg 1 ! YELLOW $end
$var reg 2 , next_state [1:0] $end
$var reg 2 - state [1:0] $end
$upscope $end
$upscope $end
$enddefinitions $end
$comment Show the parameter values. $end
$dumpall
b1 +
b11 *
b0 )
b10 (
$end
#0
$dumpvars
b0 -
b10 ,
1'
0&
0%
0$
1#
0"
0!
$end
#5
1%
#10
0%
1&
0'
#15
b1 ,
1$
0#
b10 -
1%
#20
0%
#25
1!
0$
b11 ,
b1 -
1%
#30
0%
#35
b0 ,
1"
0!
b11 -
1%
#40
0%
0&
#45
1%
#50
0%
1&
#55
1#
0"
b10 ,
b0 -
1%
#60
0%
#65
b1 ,
1$
0#
b10 -
1%
#70
0%
#75
1!
0$
b11 ,
b1 -
1%
