day-24/self_check_full_adder.v
module full_adder (
    input [2:0]a,
    input [2:0]b,
    input [2:0]cin,
    output [3:0]sum,
    output [3:0]carry
);

assign {carry ,sum} = a + b + cin ;
    
endmodule

day-25/random_test_full_adder_tb.v
module random_test_full_adder_tb ;

reg [2:0]a;
reg [2:0]b;
reg [2:0]cin;

wire [3:0]sum;
wire [3:0]carry;

integer i , j ,k;

full_adder uut(
    .a(a),
    .b(b),
    .cin(cin),
    .sum(sum),
    .carry(carry)
);

initial begin
    $dumpfile("random_test_full_adder.vcd");
    $dumpvars(0,random_test_full_adder_tb);
    

    for (i = 0; i < 8 ; i++) begin
        for (j = 0; j < 8 ; j++ ) begin
            for (k =0 ; k < 8; k++ ) begin

            a = $random;
            b = $random;
            cin = $random;
            #10;
            if ({carry,sum} == (a + b + cin)) begin
                $display("PASS time=%0t | a=%b | b=%b | c_in=%b | sum=%b |carry=%b |",$time,a,b,cin,sum,carry);
            end else begin
                $display("NO time=%0t | a=%b | b=%b | c_in=%b | sum=%b |carry=%b |",$time,a,b,cin,sum,carry);
            end
                
            end
            
        end
    end
    $finish;
end
    
endmodule

day-25/random_test_full_adder.vcd
$date
	Sun Jun 07 22:58:28 2026
$end
$version
	Icarus Verilog
$end
$timescale
	1s
$end
$scope module random_test_full_adder_tb $end
$var wire 4 ! sum [3:0] $end
$var wire 4 " carry [3:0] $end
$var reg 3 # a [2:0] $end
$var reg 3 $ b [2:0] $end
$var reg 3 % cin [2:0] $end
$var integer 32 & i [31:0] $end
$var integer 32 ' j [31:0] $end
$var integer 32 ( k [31:0] $end
$scope module uut $end
$var wire 3 ) a [2:0] $end
$var wire 3 * b [2:0] $end
$var wire 3 + cin [2:0] $end
$var wire 4 , sum [3:0] $end
$var wire 4 - carry [3:0] $end
$upscope $end
$upscope $end
$enddefinitions $end
$comment Show the parameter values. $end
$dumpall
$end
#0
$dumpvars
b0 -
b110 ,
b1 +
b1 *
b100 )
b0 (
b0 '
b0 &
b1 %
b1 $
b100 #
b0 "
b110 !
$end
#10
b1101 !
b1101 ,
b101 %
b101 +
b101 $
b101 *
b11 #
b11 )
b1 (
#20
b1000 !
b1000 ,
b1 %
b1 +
b10 $
b10 *
b101 #
b101 )
b10 (
#30
b1 "
b1 -
b0 !
b0 ,
b101 %
b101 +
b110 $
b110 *
b11 (
#40
b1010 !
b1010 ,
b0 "
b0 -
b1 %
b1 +
b100 $
b100 *
b100 (
#50
b1101 !
b1101 ,
b10 %
b10 +
b101 $
b101 *
b110 #
b110 )
b101 (
#60
b1110 !
b1110 ,
b111 $
b111 *
b101 #
b101 )
b110 (
#70
b1111 !
b1111 ,
b110 %
b110 +
b10 $
b10 *
b111 #
b111 )
b111 (
#80
b1001 !
b1001 ,
b100 %
b100 +
b101 $
b101 *
b0 #
b0 )
b1 '
b0 (
#90
b1111 !
b1111 ,
b101 %
b101 +
b101 #
b101 )
b1 (
#100
b101 !
b101 ,
b0 %
b0 +
b10 $
b10 *
b11 #
b11 )
b10 (
#110
b111 !
b111 ,
b101 %
b101 +
b0 #
b0 )
b11 (
#120
b1110 !
b1110 ,
b11 $
b11 *
b110 #
b110 )
b100 (
#130
b1011 !
b1011 ,
b11 #
b11 )
b101 (
#140
b1101 !
b1101 ,
b110 $
b110 *
b10 #
b10 )
b110 (
#150
b1100 !
b1100 ,
b10 %
b10 +
b11 $
b11 *
b111 #
b111 )
b111 (
#160
b1000 !
b1000 ,
b100 $
b100 *
b10 #
b10 )
b10 '
b0 (
#170
b11 !
b11 ,
b0 %
b0 +
b1 $
b1 *
b1 (
#180
b100 !
b100 ,
b11 %
b11 +
b0 #
b0 )
b10 (
#190
b1 "
b1 -
b10 !
b10 ,
b110 %
b110 +
b110 $
b110 *
b110 #
b110 )
b11 (
#200
b0 "
b0 -
b1001 !
b1001 ,
b11 %
b11 +
b10 $
b10 *
b100 #
b100 )
b100 (
#210
b1101 !
b1101 ,
b111 %
b111 +
b101 $
b101 *
b1 #
b1 )
b101 (
#220
b1011 !
b1011 ,
b110 %
b110 +
b10 $
b10 *
b11 #
b11 )
b110 (
#230
b111 !
b111 ,
b1 %
b1 +
b1 $
b1 *
b101 #
b101 )
b111 (
#240
b1101 !
b1101 ,
b111 %
b111 +
b100 $
b100 *
b10 #
b10 )
b11 '
b0 (
#250
b1110 !
b1110 ,
b0 $
b0 *
b111 #
b111 )
b1 (
#260
b11 %
b11 +
b100 $
b100 *
b10 (
#270
b10 !
b10 ,
b0 %
b0 +
b1 $
b1 *
b1 #
b1 )
b11 (
#280
b1110 !
b1110 ,
b110 %
b110 +
b111 #
b111 )
b100 (
#290
b110 !
b110 ,
b0 %
b0 +
b10 $
b10 *
b100 #
b100 )
b101 (
#300
b1110 !
b1110 ,
b10 %
b10 +
b101 $
b101 *
b111 #
b111 )
b110 (
#310
b1100 !
b1100 ,
b1 %
b1 +
b110 #
b110 )
b111 (
#320
b1111 !
b1111 ,
b101 %
b101 +
b11 $
b11 *
b111 #
b111 )
b100 '
b0 (
#330
b100 !
b100 ,
b1 %
b1 +
b0 #
b0 )
b1 (
#340
b1001 !
b1001 ,
b0 %
b0 +
b10 $
b10 *
b111 #
b111 )
b10 (
#350
b1 "
b1 -
b0 !
b0 ,
b100 %
b100 +
b110 $
b110 *
b110 #
b110 )
b11 (
#360
b1011 !
b1011 ,
b0 "
b0 -
b11 %
b11 +
b10 #
b10 )
b100 (
#370
b1101 !
b1101 ,
b111 $
b111 *
b11 #
b11 )
b101 (
#380
b10 !
b10 ,
b1 "
b1 -
b111 %
b111 +
b100 $
b100 *
b111 #
b111 )
b110 (
#390
b1011 !
b1011 ,
b0 "
b0 -
b10 %
b10 +
b110 $
b110 *
b11 #
b11 )
b111 (
#400
b1000 !
b1000 ,
b101 $
b101 *
b1 #
b1 )
b101 '
b0 (
#410
b1 "
b1 -
b1 !
b1 ,
b111 %
b111 +
b101 #
b101 )
b1 (
#420
b101 !
b101 ,
b0 "
b0 -
b0 %
b0 +
b100 $
b100 *
b1 #
b1 )
b10 (
#430
b1011 !
b1011 ,
b110 %
b110 +
b11 $
b11 *
b10 #
b10 )
b11 (
#440
b101 %
b101 +
b10 $
b10 *
b100 #
b100 )
b100 (
#450
b1111 !
b1111 ,
b110 %
b110 +
b110 $
b110 *
b11 #
b11 )
b101 (
#460
b10 $
b10 *
b111 #
b111 )
b110 (
#470
b1 !
b1 ,
b0 %
b0 +
b1 $
b1 *
b0 #
b0 )
b111 (
#480
b1011 !
b1011 ,
b100 %
b100 +
b11 $
b11 *
b100 #
b100 )
b110 '
b0 (
#490
b1001 !
b1001 ,
b101 %
b101 +
b1 #
b1 )
b1 (
#500
b1100 !
b1100 ,
b110 %
b110 +
b101 $
b101 *
b10 (
#510
b1101 !
b1101 ,
b101 %
b101 +
b110 $
b110 *
b10 #
b10 )
b11 (
#520
b1 !
b1 ,
b1 "
b1 -
b111 %
b111 +
b100 $
b100 *
b110 #
b110 )
b100 (
#530
b101 !
b101 ,
b0 "
b0 -
b0 %
b0 +
b1 #
b1 )
b101 (
#540
b1100 !
b1100 ,
b111 %
b111 +
b101 $
b101 *
b0 #
b0 )
b110 (
#550
b1010 !
b1010 ,
b100 %
b100 +
b0 $
b0 *
b110 #
b110 )
b111 (
#560
b1 $
b1 *
b101 #
b101 )
b111 '
b0 (
#570
b1101 !
b1101 ,
b101 %
b101 +
b10 $
b10 *
b110 #
b110 )
b1 (
#580
b1001 !
b1001 ,
b11 %
b11 +
b0 $
b0 *
b10 (
#590
b1010 !
b1010 ,
b10 %
b10 +
b110 $
b110 *
b10 #
b10 )
b11 (
#600
b1000 !
b1000 ,
b1 %
b1 +
b10 $
b10 *
b101 #
b101 )
b100 (
#610
b1101 !
b1101 ,
b0 %
b0 +
b110 $
b110 *
b111 #
b111 )
b101 (
#620
b1 "
b1 -
b1 !
b1 ,
b101 %
b101 +
b110 #
b110 )
b110 (
#630
b1010 !
b1010 ,
b0 "
b0 -
b0 %
b0 +
b100 #
b100 )
b111 (
#640
b1 "
b1 -
b0 !
b0 ,
b111 %
b111 +
b11 $
b11 *
b110 #
b110 )
b1 &
b0 '
b0 (
#650
b100 !
b100 ,
b0 "
b0 -
b1 %
b1 +
b10 $
b10 *
b1 #
b1 )
b1 (
#660
b1110 !
b1110 ,
b110 %
b110 +
b1 $
b1 *
b111 #
b111 )
b10 (
#670
b1010 !
b1010 ,
b101 %
b101 +
b101 $
b101 *
b0 #
b0 )
b11 (
#680
b111 !
b111 ,
b1 $
b1 *
b1 #
b1 )
b100 (
#690
b110 !
b110 ,
b11 %
b11 +
b11 $
b11 *
b0 #
b0 )
b101 (
#700
b1100 !
b1100 ,
b110 %
b110 +
b10 $
b10 *
b100 #
b100 )
b110 (
#710
b10 !
b10 ,
b1 %
b1 +
b1 $
b1 *
b0 #
b0 )
b111 (
#720
b1 "
b1 -
b11 !
b11 ,
b111 %
b111 +
b110 $
b110 *
b110 #
b110 )
b1 '
b0 (
#730
b1001 !
b1001 ,
b0 "
b0 -
b101 %
b101 +
b10 $
b10 *
b10 #
b10 )
b1 (
#740
b111 !
b111 ,
b1 %
b1 +
b0 $
b0 *
b110 #
b110 )
b10 (
#750
b101 !
b101 ,
b11 %
b11 +
b10 $
b10 *
b0 #
b0 )
b11 (
#760
b1 "
b1 -
b0 !
b0 ,
b110 %
b110 +
b111 $
b111 *
b11 #
b11 )
b100 (
#770
b111 !
b111 ,
b0 "
b0 -
b1 %
b1 +
b100 $
b100 *
b10 #
b10 )
b101 (
#780
b1101 !
b1101 ,
b111 %
b111 +
b110 (
#790
b1010 !
b1010 ,
b10 %
b10 +
b10 $
b10 *
b110 #
b110 )
b111 (
#800
b1011 !
b1011 ,
b100 %
b100 +
b101 $
b101 *
b10 #
b10 )
b10 '
b0 (
#810
b111 !
b111 ,
b1 %
b1 +
b10 $
b10 *
b100 #
b100 )
b1 (
#820
b1010 !
b1010 ,
b11 %
b11 +
b110 $
b110 *
b1 #
b1 )
b10 (
#830
b1011 !
b1011 ,
b1 %
b1 +
b111 $
b111 *
b11 #
b11 )
b11 (
#840
b1 "
b1 -
b10 !
b10 ,
b111 %
b111 +
b101 $
b101 *
b110 #
b110 )
b100 (
#850
b1001 !
b1001 ,
b0 "
b0 -
b110 %
b110 +
b0 $
b0 *
b11 #
b11 )
b101 (
#860
b101 !
b101 ,
b0 %
b0 +
b10 $
b10 *
b110 (
#870
b1010 !
b1010 ,
b10 %
b10 +
b11 $
b11 *
b101 #
b101 )
b111 (
#880
b1111 !
b1111 ,
b100 %
b100 +
b101 $
b101 *
b110 #
b110 )
b11 '
b0 (
#890
b111 !
b111 ,
b110 %
b110 +
b1 $
b1 *
b0 #
b0 )
b1 (
#900
b100 !
b100 ,
b0 %
b0 +
b11 $
b11 *
b1 #
b1 )
b10 (
#910
b1100 !
b1100 ,
b11 %
b11 +
b110 $
b110 *
b11 #
b11 )
b11 (
#920
b1001 !
b1001 ,
b100 $
b100 *
b10 #
b10 )
b100 (
#930
b10 !
b10 ,
b0 %
b0 +
b10 $
b10 *
b0 #
b0 )
b101 (
#940
b111 !
b111 ,
b1 %
b1 +
b101 $
b101 *
b1 #
b1 )
b110 (
#950
b100 !
b100 ,
b0 %
b0 +
b1 $
b1 *
b11 #
b11 )
b111 (
#960
b1111 !
b1111 ,
b111 %
b111 +
b111 #
b111 )
b100 '
b0 (
#970
b1010 !
b1010 ,
b110 %
b110 +
b0 $
b0 *
b100 #
b100 )
b1 (
#980
b1100 !
b1100 ,
b10 $
b10 *
b10 (
#990
b1011 !
b1011 ,
b101 %
b101 +
b101 $
b101 *
b1 #
b1 )
b11 (
#1000
b1101 !
b1101 ,
b11 #
b11 )
b100 (
#1010
b10 !
b10 ,
b1 "
b1 -
b111 %
b111 +
b100 $
b100 *
b111 #
b111 )
b101 (
#1020
b1001 !
b1001 ,
b0 "
b0 -
b1 %
b1 +
b1 $
b1 *
b110 (
#1030
b101 !
b101 ,
b11 #
b11 )
b111 (
#1040
b10 %
b10 +
b10 $
b10 *
b1 #
b1 )
b101 '
b0 (
#1050
b1100 !
b1100 ,
b100 %
b100 +
b11 $
b11 *
b101 #
b101 )
b1 (
#1060
b1000 !
b1000 ,
b0 %
b0 +
b110 $
b110 *
b10 #
b10 )
b10 (
#1070
b1101 !
b1101 ,
b111 #
b111 )
b11 (
#1080
b0 !
b0 ,
b0 $
b0 *
b0 #
b0 )
b100 (
#1090
b1011 !
b1011 ,
b101 $
b101 *
b110 #
b110 )
b101 (
#1100
b101 !
b101 ,
b1 $
b1 *
b100 #
b100 )
b110 (
#1110
b1000 !
b1000 ,
b10 %
b10 +
b10 $
b10 *
b111 (
#1120
b1101 !
b1101 ,
b111 %
b111 +
b1 $
b1 *
b101 #
b101 )
b110 '
b0 (
#1130
b1010 !
b1010 ,
b110 %
b110 +
b11 #
b11 )
b1 (
#1140
b1011 !
b1011 ,
b101 %
b101 +
b101 #
b101 )
b10 (
#1150
b1101 !
b1101 ,
b100 %
b100 +
b111 $
b111 *
b10 #
b10 )
b11 (
#1160
b1000 !
b1000 ,
b11 %
b11 +
b1 $
b1 *
b100 #
b100 )
b100 (
#1170
b1 "
b1 -
b11 !
b11 ,
b110 %
b110 +
b111 $
b111 *
b110 #
b110 )
b101 (
#1180
b0 "
b0 -
b1001 !
b1001 ,
b0 %
b0 +
b101 $
b101 *
b100 #
b100 )
b110 (
#1190
b110 !
b110 ,
b100 %
b100 +
b10 $
b10 *
b0 #
b0 )
b111 (
#1200
b1101 !
b1101 ,
b11 %
b11 +
b101 $
b101 *
b101 #
b101 )
b111 '
b0 (
#1210
b1100 !
b1100 ,
b101 %
b101 +
b110 $
b110 *
b1 #
b1 )
b1 (
#1220
b1101 !
b1101 ,
b11 %
b11 +
b111 $
b111 *
b11 #
b11 )
b10 (
#1230
b1001 !
b1001 ,
b1 %
b1 +
b101 $
b101 *
b11 (
#1240
b0 %
b0 +
b100 #
b100 )
b100 (
#1250
b111 !
b111 ,
b10 $
b10 *
b101 #
b101 )
b101 (
#1260
b1011 !
b1011 ,
b100 %
b100 +
b110 (
#1270
b1010 !
b1010 ,
b0 %
b0 +
b100 $
b100 *
b110 #
b110 )
b111 (
#1280
b1101 !
b1101 ,
b100 %
b100 +
b10 $
b10 *
b111 #
b111 )
b10 &
b0 '
b0 (
#1290
b110 !
b110 ,
b0 %
b0 +
b100 $
b100 *
b10 #
b10 )
b1 (
#1300
b1011 !
b1011 ,
b110 %
b110 +
b11 $
b11 *
b10 (
#1310
b1001 !
b1001 ,
b10 %
b10 +
b10 $
b10 *
b101 #
b101 )
b11 (
#1320
b1010 !
b1010 ,
b101 %
b101 +
b100 $
b100 *
b1 #
b1 )
b100 (
#1330
b1110 !
b1110 ,
b111 %
b111 +
b11 #
b11 )
b101 (
#1340
b1011 !
b1011 ,
b100 %
b100 +
b1 $
b1 *
b110 #
b110 )
b110 (
#1350
b1000 !
b1000 ,
b100 $
b100 *
b0 #
b0 )
b111 (
#1360
b1010 !
b1010 ,
b1 %
b1 +
b10 $
b10 *
b111 #
b111 )
b1 '
b0 (
#1370
b110 !
b110 ,
b11 %
b11 +
b11 $
b11 *
b0 #
b0 )
b1 (
#1380
b1011 !
b1011 ,
b100 %
b100 +
b100 #
b100 )
b10 (
#1390
b1001 !
b1001 ,
b111 %
b111 +
b1 $
b1 *
b1 #
b1 )
b11 (
#1400
b1 "
b1 -
b0 !
b0 ,
b101 %
b101 +
b111 $
b111 *
b100 #
b100 )
b100 (
#1410
b11 !
b11 ,
b0 "
b0 -
b1 %
b1 +
b10 $
b10 *
b0 #
b0 )
b101 (
#1420
b101 !
b101 ,
b100 %
b100 +
b0 $
b0 *
b1 #
b1 )
b110 (
#1430
b1000 !
b1000 ,
b10 %
b10 +
b11 $
b11 *
b11 #
b11 )
b111 (
#1440
b111 !
b111 ,
b101 $
b101 *
b0 #
b0 )
b10 '
b0 (
#1450
b1000 !
b1000 ,
b1 %
b1 +
b11 $
b11 *
b100 #
b100 )
b1 (
#1460
b101 !
b101 ,
b10 $
b10 *
b10 #
b10 )
b10 (
#1470
b1101 !
b1101 ,
b111 %
b111 +
b110 $
b110 *
b0 #
b0 )
b11 (
#1480
b1100 !
b1100 ,
b11 %
b11 +
b11 #
b11 )
b100 (
#1490
b1000 !
b1000 ,
b1 %
b1 +
b111 $
b111 *
b0 #
b0 )
b101 (
#1500
b1010 !
b1010 ,
b101 %
b101 +
b1 $
b1 *
b100 #
b100 )
b110 (
#1510
b1000 !
b1000 ,
b1 %
b1 +
b0 $
b0 *
b111 #
b111 )
b111 (
#1520
b1010 !
b1010 ,
b10 %
b10 +
b111 $
b111 *
b1 #
b1 )
b11 '
b0 (
#1530
b111 !
b111 ,
b100 %
b100 +
b11 $
b11 *
b0 #
b0 )
b1 (
#1540
b1101 !
b1101 ,
b110 %
b110 +
b111 $
b111 *
b10 (
#1550
b1100 !
b1100 ,
b101 %
b101 +
b11 (
#1560
b1 !
b1 ,
b1 "
b1 -
b110 %
b110 +
b100 #
b100 )
b100 (
#1570
b101 !
b101 ,
b0 "
b0 -
b1 %
b1 +
b11 $
b11 *
b1 #
b1 )
b101 (
#1580
b10 %
b10 +
b0 $
b0 *
b11 #
b11 )
b110 (
#1590
b1100 !
b1100 ,
b111 %
b111 +
b101 #
b101 )
b111 (
#1600
b1110 !
b1110 ,
b1 %
b1 +
b111 $
b111 *
b110 #
b110 )
b100 '
b0 (
#1610
b1101 !
b1101 ,
b111 %
b111 +
b110 $
b110 *
b0 #
b0 )
b1 (
#1620
b1100 !
b1100 ,
b110 %
b110 +
b101 $
b101 *
b1 #
b1 )
b10 (
#1630
b101 !
b101 ,
b0 %
b0 +
b0 #
b0 )
b11 (
#1640
b110 !
b110 ,
b1 %
b1 +
b1 $
b1 *
b100 #
b100 )
b100 (
#1650
b1110 !
b1110 ,
b110 $
b110 *
b111 #
b111 )
b101 (
#1660
b101 !
b101 ,
b0 %
b0 +
b0 $
b0 *
b101 #
b101 )
b110 (
#1670
b1010 !
b1010 ,
b1 %
b1 +
b111 $
b111 *
b10 #
b10 )
b111 (
#1680
b1101 !
b1101 ,
b10 %
b10 +
b110 $
b110 *
b101 #
b101 )
b101 '
b0 (
#1690
b1100 !
b1100 ,
b111 %
b111 +
b1 $
b1 *
b100 #
b100 )
b1 (
#1700
b10 %
b10 +
b111 $
b111 *
b11 #
b11 )
b10 (
#1710
b111 !
b111 ,
b11 %
b11 +
b11 $
b11 *
b1 #
b1 )
b11 (
#1720
b1101 !
b1101 ,
b111 %
b111 +
b1 $
b1 *
b101 #
b101 )
b100 (
#1730
b100 !
b100 ,
b1 %
b1 +
b10 $
b10 *
b1 #
b1 )
b101 (
#1740
b1000 !
b1000 ,
b10 %
b10 +
b100 $
b100 *
b10 #
b10 )
b110 (
#1750
b1011 !
b1011 ,
b101 %
b101 +
b1 $
b1 *
b101 #
b101 )
b111 (
#1760
b111 !
b111 ,
b1 %
b1 +
b110 '
b0 (
#1770
b1111 !
b1111 ,
b101 %
b101 +
b11 $
b11 *
b111 #
b111 )
b1 (
#1780
b1000 !
b1000 ,
b10 %
b10 +
b110 $
b110 *
b0 #
b0 )
b10 (
#1790
b1011 !
b1011 ,
b100 %
b100 +
b10 $
b10 *
b101 #
b101 )
b11 (
#1800
b1000 !
b1000 ,
b101 %
b101 +
b11 $
b11 *
b0 #
b0 )
b100 (
#1810
b1010 !
b1010 ,
b100 %
b100 +
b110 $
b110 *
b101 (
#1820
b100 !
b100 ,
b0 %
b0 +
b1 $
b1 *
b11 #
b11 )
b110 (
#1830
b1100 !
b1100 ,
b11 %
b11 +
b110 $
b110 *
b111 (
#1840
b1110 !
b1110 ,
b100 %
b100 +
b100 #
b100 )
b111 '
b0 (
#1850
b101 !
b101 ,
b11 %
b11 +
b1 $
b1 *
b1 #
b1 )
b1 (
#1860
b1101 !
b1101 ,
b100 %
b100 +
b101 $
b101 *
b100 #
b100 )
b10 (
#1870
b1000 !
b1000 ,
b101 %
b101 +
b10 $
b10 *
b1 #
b1 )
b11 (
#1880
b1101 !
b1101 ,
b10 %
b10 +
b110 $
b110 *
b101 #
b101 )
b100 (
#1890
b101 !
b101 ,
b101 %
b101 +
b0 $
b0 *
b0 #
b0 )
b101 (
#1900
b111 !
b111 ,
b0 %
b0 +
b111 #
b111 )
b110 (
#1910
b1100 !
b1100 ,
b11 %
b11 +
b100 $
b100 *
b101 #
b101 )
b111 (
#1920
b1010 !
b1010 ,
b101 %
b101 +
b101 $
b101 *
b0 #
b0 )
b11 &
b0 '
b0 (
#1930
b110 !
b110 ,
b1 %
b1 +
b1 (
#1940
b100 !
b100 ,
b0 %
b0 +
b0 $
b0 *
b100 #
b100 )
b10 (
#1950
b110 !
b110 ,
b101 %
b101 +
b1 $
b1 *
b0 #
b0 )
b11 (
#1960
b1111 !
b1111 ,
b101 $
b101 *
b101 #
b101 )
b100 (
#1970
b1010 !
b1010 ,
b100 %
b100 +
b10 $
b10 *
b100 #
b100 )
b101 (
#1980
b1000 !
b1000 ,
b10 %
b10 +
b110 $
b110 *
b0 #
b0 )
b110 (
#1990
b1 "
b1 -
b0 !
b0 ,
b11 %
b11 +
b111 $
b111 *
b110 #
b110 )
b111 (
#2000
b1 !
b1 ,
b101 %
b101 +
b101 #
b101 )
b1 '
b0 (
#2010
b1010 !
b1010 ,
b0 "
b0 -
b110 %
b110 +
b1 $
b1 *
b11 #
b11 )
b1 (
#2020
b110 !
b110 ,
b0 %
b0 +
b110 $
b110 *
b0 #
b0 )
b10 (
#2030
b111 !
b111 ,
b1 %
b1 +
b100 $
b100 *
b10 #
b10 )
b11 (
#2040
b1010 !
b1010 ,
b111 %
b111 +
b0 $
b0 *
b11 #
b11 )
b100 (
#2050
b101 %
b101 +
b101 $
b101 *
b0 #
b0 )
b101 (
#2060
b1011 !
b1011 ,
b100 %
b100 +
b100 $
b100 *
b11 #
b11 )
b110 (
#2070
b1010 !
b1010 ,
b101 %
b101 +
b1 $
b1 *
b100 #
b100 )
b111 (
#2080
b1001 !
b1001 ,
b0 %
b0 +
b11 $
b11 *
b110 #
b110 )
b10 '
b0 (
#2090
b1110 !
b1110 ,
b110 %
b110 +
b100 $
b100 *
b100 #
b100 )
b1 (
#2100
b111 !
b111 ,
b101 %
b101 +
b0 $
b0 *
b10 #
b10 )
b10 (
#2110
b11 %
b11 +
b10 $
b10 *
b11 (
#2120
b1 %
b1 +
b100 $
b100 *
b100 (
#2130
b110 !
b110 ,
b0 %
b0 +
b11 $
b11 *
b11 #
b11 )
b101 (
#2140
b1010 !
b1010 ,
b111 %
b111 +
b1 $
b1 *
b10 #
b10 )
b110 (
#2150
b1000 !
b1000 ,
b0 %
b0 +
b101 $
b101 *
b11 #
b11 )
b111 (
#2160
b1111 !
b1111 ,
b11 %
b11 +
b111 $
b111 *
b101 #
b101 )
b11 '
b0 (
#2170
b1000 !
b1000 ,
b101 %
b101 +
b0 $
b0 *
b11 #
b11 )
b1 (
#2180
b1101 !
b1101 ,
b111 %
b111 +
b100 $
b100 *
b10 #
b10 )
b10 (
#2190
b1001 !
b1001 ,
b1 %
b1 +
b10 $
b10 *
b110 #
b110 )
b11 (
#2200
b1100 !
b1100 ,
b10 %
b10 +
b110 $
b110 *
b100 #
b100 )
b100 (
#2210
b1010 !
b1010 ,
b100 %
b100 +
b0 #
b0 )
b101 (
#2220
b1000 !
b1000 ,
b11 $
b11 *
b1 #
b1 )
b110 (
#2230
b1100 !
b1100 ,
b1 %
b1 +
b111 $
b111 *
b100 #
b100 )
b111 (
#2240
b1001 !
b1001 ,
b101 $
b101 *
b11 #
b11 )
b100 '
b0 (
#2250
b1110 !
b1110 ,
b0 %
b0 +
b111 $
b111 *
b111 #
b111 )
b1 (
#2260
b1011 !
b1011 ,
b10 %
b10 +
b110 $
b110 *
b11 #
b11 )
b10 (
#2270
b1010 !
b1010 ,
b111 %
b111 +
b1 $
b1 *
b10 #
b10 )
b11 (
#2280
b1100 !
b1100 ,
b101 %
b101 +
b110 #
b110 )
b100 (
#2290
b1001 !
b1001 ,
b0 %
b0 +
b100 $
b100 *
b101 #
b101 )
b101 (
#2300
b1011 !
b1011 ,
b101 %
b101 +
b10 $
b10 *
b100 #
b100 )
b110 (
#2310
b1 "
b1 -
b0 !
b0 ,
b110 %
b110 +
b11 $
b11 *
b111 #
b111 )
b111 (
#2320
b1011 !
b1011 ,
b0 "
b0 -
b0 %
b0 +
b110 $
b110 *
b101 #
b101 )
b101 '
b0 (
#2330
b1010 !
b1010 ,
b110 %
b110 +
b0 $
b0 *
b100 #
b100 )
b1 (
#2340
b111 !
b111 ,
b101 %
b101 +
b10 #
b10 )
b10 (
#2350
b1111 !
b1111 ,
b11 %
b11 +
b110 $
b110 *
b110 #
b110 )
b11 (
#2360
b1101 !
b1101 ,
b111 %
b111 +
b11 $
b11 *
b11 #
b11 )
b100 (
#2370
b10 %
b10 +
b100 $
b100 *
b111 #
b111 )
b101 (
#2380
b11 %
b11 +
b110 #
b110 )
b110 (
#2390
b1011 !
b1011 ,
b100 %
b100 +
b11 #
b11 )
b111 (
#2400
b101 %
b101 +
b1 $
b1 *
b101 #
b101 )
b110 '
b0 (
#2410
b10 !
b10 ,
b0 %
b0 +
b1 #
b1 )
b1 (
#2420
b1 "
b1 -
b1 !
b1 ,
b111 %
b111 +
b100 $
b100 *
b110 #
b110 )
b10 (
#2430
b1001 !
b1001 ,
b0 "
b0 -
b110 %
b110 +
b11 $
b11 *
b0 #
b0 )
b11 (
#2440
b100 !
b100 ,
b0 %
b0 +
b0 $
b0 *
b100 #
b100 )
b100 (
#2450
b11 !
b11 ,
b11 $
b11 *
b0 #
b0 )
b101 (
#2460
b100 !
b100 ,
b1 #
b1 )
b110 (
#2470
b1 "
b1 -
b0 !
b0 ,
b10 %
b10 +
b111 $
b111 *
b111 #
b111 )
b111 (
#2480
b1000 !
b1000 ,
b0 "
b0 -
b11 %
b11 +
b0 $
b0 *
b101 #
b101 )
b111 '
b0 (
#2490
b111 !
b111 ,
b100 %
b100 +
b10 $
b10 *
b1 #
b1 )
b1 (
#2500
b1010 !
b1010 ,
b0 %
b0 +
b101 $
b101 *
b101 #
b101 )
b10 (
#2510
b1000 !
b1000 ,
b100 $
b100 *
b100 #
b100 )
b11 (
#2520
b1011 !
b1011 ,
b101 %
b101 +
b11 $
b11 *
b11 #
b11 )
b100 (
#2530
b111 %
b111 +
b0 $
b0 *
b100 #
b100 )
b101 (
#2540
b1101 !
b1101 ,
b11 %
b11 +
b11 $
b11 *
b111 #
b111 )
b110 (
#2550
b11 !
b11 ,
b1 %
b1 +
b10 $
b10 *
b0 #
b0 )
b111 (
#2560
b1111 !
b1111 ,
b110 %
b110 +
b111 #
b111 )
b100 &
b0 '
b0 (
#2570
b1110 !
b1110 ,
b11 %
b11 +
b100 $
b100 *
b1 (
#2580
b1010 !
b1010 ,
b101 %
b101 +
b101 $
b101 *
b0 #
b0 )
b10 (
#2590
b100 !
b100 ,
b10 %
b10 +
b0 $
b0 *
b10 #
b10 )
b11 (
#2600
b11 !
b11 ,
b11 %
b11 +
b0 #
b0 )
b100 (
#2610
b1011 !
b1011 ,
b10 %
b10 +
b101 $
b101 *
b100 #
b100 )
b101 (
#2620
b1101 !
b1101 ,
b11 %
b11 +
b100 $
b100 *
b110 #
b110 )
b110 (
#2630
b111 !
b111 ,
b111 %
b111 +
b0 $
b0 *
b0 #
b0 )
b111 (
#2640
b110 !
b110 ,
b1 %
b1 +
b101 $
b101 *
b1 '
b0 (
#2650
b1011 !
b1011 ,
b101 %
b101 +
b11 $
b11 *
b11 #
b11 )
b1 (
#2660
b1010 !
b1010 ,
b111 %
b111 +
b0 #
b0 )
b10 (
#2670
b101 !
b101 ,
b101 %
b101 +
b0 $
b0 *
b11 (
#2680
b1000 !
b1000 ,
b1 %
b1 +
b1 $
b1 *
b110 #
b110 )
b100 (
#2690
b1111 !
b1111 ,
b11 %
b11 +
b111 $
b111 *
b101 #
b101 )
b101 (
#2700
b1001 !
b1001 ,
b0 %
b0 +
b11 $
b11 *
b110 #
b110 )
b110 (
#2710
b110 !
b110 ,
b101 %
b101 +
b0 $
b0 *
b1 #
b1 )
b111 (
#2720
b1011 !
b1011 ,
b100 %
b100 +
b100 $
b100 *
b11 #
b11 )
b10 '
b0 (
#2730
b1 "
b1 -
b11 !
b11 ,
b111 %
b111 +
b110 $
b110 *
b110 #
b110 )
b1 (
#2740
b0 "
b0 -
b101 !
b101 ,
b10 %
b10 +
b0 $
b0 *
b11 #
b11 )
b10 (
#2750
b1 "
b1 -
b11 !
b11 ,
b111 %
b111 +
b101 $
b101 *
b111 #
b111 )
b11 (
#2760
b0 "
b0 -
b1010 !
b1010 ,
b0 %
b0 +
b101 #
b101 )
b100 (
#2770
b100 $
b100 *
b110 #
b110 )
b101 (
#2780
b1001 !
b1001 ,
b100 %
b100 +
b1 #
b1 )
b110 (
#2790
b1110 !
b1110 ,
b1 %
b1 +
b110 $
b110 *
b111 #
b111 )
b111 (
#2800
b1101 !
b1101 ,
b101 %
b101 +
b10 #
b10 )
b11 '
b0 (
#2810
b100 !
b100 ,
b10 %
b10 +
b0 $
b0 *
b1 (
#2820
b111 !
b111 ,
b11 $
b11 *
b10 (
#2830
b1000 !
b1000 ,
b11 #
b11 )
b11 (
#2840
b1011 !
b1011 ,
b110 %
b110 +
b1 $
b1 *
b100 #
b100 )
b100 (
#2850
b111 %
b111 +
b11 $
b11 *
b1 #
b1 )
b101 (
#2860
b10 !
b10 ,
b1 %
b1 +
b0 $
b0 *
b110 (
#2870
b1011 !
b1011 ,
b100 $
b100 *
b110 #
b110 )
b111 (
