day-11/t_r.v
module t_ff_r(
    input reset, t, clk,
    output reg q 
 );
 always @(posedge clk) begin

    if (reset == 0) begin
     if (t ==0) begin
        q <= ~q ;        
     end    
     else begin
        q <= q ;        
     end    
   end 
   else begin
    q <= 1'b0 ;    
    end
    
    
 end
   
endmodule

day-11/t_r_tb.v
module tff_r ;

reg t, clk, r;
wire q;

t_ff_r uut(
    .t(t),
    .clk(clk),
    .reset(r),
    .q(q)

);

always #5 clk = ~clk;

initial begin
    $dumpfile("tff_reset.vcd");
    $dumpvars(0, tff_r);
    clk=0;
    $display("'/ T filopflop with reset button");
    $monitor("time=%0t, reset=%b, clk=%b, t=%b, q=%b",$time,r,clk,t,q);
    r=1;
    #10;
    r=0;

    #10 t=0;
    #10 t=1;
    #10 t=0;
    #10 t=1;
    #10

    $finish;
end
    
endmodule

day-11/tff_reset.vcd
$date
	Thu Jun 04 13:03:43 2026
$end
$version
	Icarus Verilog
$end
$timescale
	1s
$end
$scope module tff_r $end
$var wire 1 ! q $end
$var reg 1 " clk $end
$var reg 1 # r $end
$var reg 1 $ t $end
$scope module uut $end
$var wire 1 " clk $end
$var wire 1 # reset $end
$var wire 1 $ t $end
$var reg 1 ! q $end
$upscope $end
$upscope $end
$enddefinitions $end
$comment Show the parameter values. $end
$dumpall
$end
#0
$dumpvars
x$
1#
0"
x!
$end
#5
0!
1"
#10
0"
0#
#15
1"
#20
0"
0$
#25
1!
1"
#30
0"
1$
#35
1"
#40
0"
0$
#45
0!
1"
#50
0"
1$
