day-17/3x8_encoder.v
/*
Challenge 1

8-to-3 Encoder

*/

module encoder(
    input [7:0]a,
    output reg [2:0]y
);
    always @(*) begin
        case (a)
            8'b00000001 : y=000;
            8'b00000010 : y=001;
            8'b00000100 : y=010;
            8'b00001000 : y=011;
            8'b00010000 : y=100;
            8'b00100000 : y=101;
            8'b01000000 : y=110;
            8'b10000000 : y=111;
            
        endcase
        
    end
endmodule

day-17/p_encoder_tb.v
module encoder_tb;
reg [7:0]a;
wire [2:0]y;
    
    encoder uut(
        .a(a),
        .y(y)
    );

    initial begin
        $dumpfile("Priority_encoder.vcd");
        $dumpvars(0,encoder_tb);
        $monitor("time=%0t | a=%b| y=%b",$time,a,y);
              

         a=8'b00000001;
        #10;

          a=8'b00000010;
        #10;

         a=8'b00000100;
        #10;

          a=8'b00001000;
        #10;

         a=8'b00010000;
        #10;

          a=8'b00100000;
        #10;

          a=8'b01000000;
        #10;

          a=8'b10000000;
        #10;

        $finish;

    end
endmodule

day-17/3x8_encoder.vcd
$date
	Fri Jun 05 10:41:05 2026
$end
$version
	Icarus Verilog
$end
$timescale
	1s
$end
$scope module encoder_tb $end
$var wire 3 ! y [2:0] $end
$var reg 8 " a [7:0] $end
$scope module uut $end
$var wire 8 # a [7:0] $end
$var reg 3 $ y [2:0] $end
$upscope $end
$upscope $end
$enddefinitions $end
$comment Show the parameter values. $end
$dumpall
$end
#0
$dumpvars
b0 $
b1 #
b1 "
b0 !
$end
#10
b1 !
b1 $
b10 "
b10 #
#20
b10 !
b10 $
b100 "
b100 #
#30
b11 !
b11 $
b1000 "
b1000 #
#40
b100 !
b100 $
b10000 "
b10000 #
#50
b101 !
b101 $
b100000 "
b100000 #
#60
b110 !
b110 $
b1000000 "
b1000000 #
#70
b111 !
b111 $
b10000000 "
b10000000 #
