day-5/fullsub.v
module fullsub (
    input a, b, bin,
    output diff, borrow
);
    /*assign diff = a ^ b ^ bin;
    assign borrow = (~a & b) | (b * bin) | (!a & bin); */

    assign {diff,borrow} = a-b-bin ;

endmodule

day-5/fullsubtb.v
module fullsubtb;

reg a, b, bi;
wire br, d;

fullsub uut(
    .a(a),
    .b(b),
    .bin(bi),
    .diff(d),
    .borrow(br)
);

initial begin
    $dumpfile("fullsub.vcd");
    $dumpvars(0, fullsubtb);

    a=0; b=0; bi=0;
    #10;
    $display("%b %b %b | %b %b",a,b,bi,d,br);

    a=0; b=0; bi=1;
    #10;
    $display("%b %b %b | %b %b",a,b,bi,d,br);

    a=0; b=1; bi=0;
    #10;
    $display("%b %b %b | %b %b",a,b,bi,d,br);

    a=0; b=1; bi=1;
    #10;
    $display("%b %b %b | %b %b",a,b,bi,d,br);

    a=1; b=0; bi=0;
    #10;
    $display("%b %b %b | %b %b",a,b,bi,d,br);

    a=1; b=0; bi=1;
    #10;
    $display("%b %b %b | %b %b",a,b,bi,d,br);

    a=1; b=1; bi=0;
    #10;
    $display("%b %b %b | %b %b",a,b,bi,d,br);

    a=1; b=1; bi=1;
    #10;
    $display("%b %b %b | %b %b",a,b,bi,d,br);
    $finish;

end
    
endmodule

day-5/fullsub.vcd
$date
	Tue Jun 02 00:18:52 2026
$end
$version
	Icarus Verilog
$end
$timescale
	1s
$end
$scope module fullsubtb $end
$var wire 1 ! d $end
$var wire 1 " br $end
$var reg 1 # a $end
$var reg 1 $ b $end
$var reg 1 % bi $end
$scope module uut $end
$var wire 1 # a $end
$var wire 1 $ b $end
$var wire 1 % bin $end
$var wire 1 ! diff $end
$var wire 1 " borrow $end
$upscope $end
$upscope $end
$enddefinitions $end
$comment Show the parameter values. $end
$dumpall
$end
#0
$dumpvars
0%
0$
0#
0"
0!
$end
#10
1"
1!
1%
#20
0%
1$
#30
0"
1%
#40
0!
1"
0%
0$
1#
#50
0"
1%
#60
0%
1$
#70
1"
1!
1%
