day-8/d_ff_1.v
module seq_d(
    input d,
    input clk,
    output reg q
);
    always @(posedge clk)
     begin
        q <= d;
    end
endmodule

day-8/d_ff_1tb.v
module dtb ;

reg d, clk;
wire q ;

seq_d  uut(
      .d(d),
      .clk(clk),
      .q(q)
);

always #5 clk = ~clk;


initial begin
    $dumpfile("d_ff_1.vcd");
    $dumpvars(0, dtb);

    clk=0;
    

    d=0;
    #10;

    d=1;
    #10;

    d=0;
    #10;

    d=1;
    #10;
    
    $finish;

end

endmodule

day-8/d_ff_1.vcd
$date
	Thu Jun 04 12:28:15 2026
$end
$version
	Icarus Verilog
$end
$timescale
	1s
$end
$scope module dtb $end
$var wire 1 ! q $end
$var reg 1 " clk $end
$var reg 1 # d $end
$scope module uut $end
$var wire 1 " clk $end
$var wire 1 # d $end
$var reg 1 ! q $end
$upscope $end
$upscope $end
$enddefinitions $end
$comment Show the parameter values. $end
$dumpall
$end
#0
$dumpvars
0#
0"
x!
$end
#5
0!
1"
#10
0"
1#
#15
1!
1"
#20
0"
0#
#25
0!
1"
#30
0"
1#
#35
1!
1"
