day-10/jk_ff.v
module jkff(
    input j, k, clk,
    output reg q
);

always @(posedge clk) 
begin

    case ({j,k})

    2'b00: q <= q;
    2'b01: q <= 0;
    2'b10: q <= 1;
    2'b11: q <= ~q;


     
    endcase
end



    
endmodule

day-10/jk_ff_tb.v
module jk_tb;

reg j, k, clk;
wire  q;

jkff uut(

    .q(q),
    .j(j),
    .k(k),
    .clk(clk)
);
    
    always #5 clk = ~clk;
    initial begin
        $dumpfile("jk.vcd");
        $dumpvars(0,jk_tb);

        


        $display("jk filpflop");
        
        
        clk =0;
        
        $monitor("time =%0t | clk= %b |j= %b |k= %b |q= %b ",$time,clk,j,k,q);
        
    
        
        j=0; k=0;
        #10; 

        j=0; k=1;
        #10;
        
        j=1; k=0;
        #10; 
        
        j=1; k=1;
        #10;
        
        j=1; k=1;
        #10;
        
        j=1; k=1;
        #10;

        $finish;


    end
    initial begin
        
    end
endmodule

day-10/jk.vcd
$date
	Thu Jun 04 12:47:33 2026
$end
$version
	Icarus Verilog
$end
$timescale
	1s
$end
$scope module jk_tb $end
$var wire 1 ! q $end
$var reg 1 " clk $end
$var reg 1 # j $end
$var reg 1 $ k $end
$scope module uut $end
$var wire 1 " clk $end
$var wire 1 # j $end
$var wire 1 $ k $end
$var reg 1 ! q $end
$upscope $end
$upscope $end
$enddefinitions $end
$comment Show the parameter values. $end
$dumpall
$end
#0
$dumpvars
0$
0#
0"
x!
$end
#5
1"
#10
0"
1$
#15
0!
1"
#20
0"
0$
1#
#25
1!
1"
#30
0"
1$
#35
0!
1"
#40
0"
#45
1!
1"
#50
0"
#55
0!
1"
