day-10/jk_ff_r.v
module jk_ff (
    input j, k, reset, clk,
    output reg q
);

always @(posedge clk) begin

    if (reset == 1) begin

        q <= 0;
        
    end 
    
    else begin

        case ({j,k})
        
         2'b00 : q <= q;
         2'b01 : q <= 0;
         2'b10 : q <= 1;
         2'b11 : q <= ~q;

          endcase

        
    end
    
    

end
    
endmodule

day-10/jk_r_tb.v
module jk_tb;
reg j, k, r, clk;
wire q;
jk_ff uut(
    .q(q),
    .j(j),
    .k(k),
    .reset(r),
    .clk(clk)
);
always #5 clk = ~clk;
initial begin
    $dumpfile("jk_reset.vcd");
    $dumpvars(0,jk_tb);

    j=0;
    
    k=0;
    clk=0;
    r=1;
    #10;
    r=0;

    j=0; k=0;
    #10;

    j=0; k=1;
    #10;

    j=1; k=0;
    #10;

    j=1; k=1;
    #10;

    j=1; k=1;
    #10;

    j=1; k=1;
    #10;

    $finish;

end

initial begin
    $display("jk filpflop with reset button");
    $monitor("time=%0t| clk=%b | reset=%b | j=%b | k=%b| q=%b",$time,clk,r,j,k,q);
end
    
endmodule

day-10/jk_reset.vcd
$date
	Thu Jun 04 12:49:16 2026
$end
$version
	Icarus Verilog
$end
$timescale
	1s
$end
$scope module jk_tb $end
$var wire 1 ! q $end
$var reg 1 " clk $end
$var reg 1 # j $end
$var reg 1 $ k $end
$var reg 1 % r $end
$scope module uut $end
$var wire 1 " clk $end
$var wire 1 # j $end
$var wire 1 $ k $end
$var wire 1 % reset $end
$var reg 1 ! q $end
$upscope $end
$upscope $end
$enddefinitions $end
$comment Show the parameter values. $end
$dumpall
$end
#0
$dumpvars
1%
0$
0#
0"
x!
$end
#5
0!
1"
#10
0"
0%
#15
1"
#20
0"
1$
#25
1"
#30
0"
0$
1#
#35
1!
1"
#40
0"
1$
#45
0!
1"
#50
0"
#55
1!
1"
#60
0"
#65
0!
1"
